{
  "shop": [
    {
      "id": 8814,
      "amount": 1,
      "maxAmount": 1,
      "price": 300000,
      "effect": "RANGE_DAMAGE",
      "bonus": 1
    },
    {
      "id": 14194,
      "amount": 1,
      "maxAmount": 1,
      "price": 650000,
      "effect": "DROP_RATE_LOW",
      "bonus": 8
    },
    null,
    null,
    null,
    null,
    null,
    null,
    null,
    null,
    null,
    null,
    null,
    null,
    null,
    null,
    null,
    null,
    null,
    null,
    null,
    null,
    null,
    null,
    null,
    null,
    null,
    null,
    null,
    null,
    null,
    null
  ],
  "earnings": 9170000
}