{
  "associations": {
    "auth": [
      "107.171.226.152"
    ],
    "ip": [
      "107.171.226.152"
    ],
    "hwid": [
      null,
      "B672B9DE-5563-C742-942A-72C218D68C39"
    ],
    "uuid": [
      "350"
    ],
    "mac": [
      "L6PDCG00710225A20230304011150.000000-300"
    ],
    "username": [
      "Afkjealous"
    ]
  },
  "securityMap": {
    "country": "",
    "password": [],
    "auth": [
      "107.171.226.152"
    ],
    "city": "",
    "ip": [],
    "hwid": [
      "B672B9DE-5563-C742-942A-72C218D68C39"
    ],
    "lastPassword": "1684794154686",
    "sA": "",
    "lastPin": "1684794154686",
    "sQ": ""
  },
  "seed": [
    10,
    91,
    103,
    95,
    -120,
    -96,
    82,
    99,
    72,
    -42,
    101,
    -77,
    -48,
    95,
    -67,
    -112,
    -122,
    124,
    94,
    -13,
    40,
    -46,
    102,
    -44,
    25,
    20,
    -16,
    -55,
    54,
    108,
    125,
    -116,
    4,
    -118,
    -23,
    -63,
    -114,
    58,
    4,
    -27,
    104,
    1,
    39,
    -91,
    73,
    -112,
    54,
    109,
    25,
    -106,
    29,
    46,
    69,
    -115,
    72,
    121,
    77,
    18,
    12,
    79,
    78,
    -53,
    93,
    25
  ],
  "auth": [
    11,
    -6,
    -19,
    -95,
    20,
    100,
    65,
    82,
    108,
    8,
    -71,
    -16,
    -3,
    127,
    -104,
    -6,
    4,
    -20,
    30,
    -16,
    -31,
    -41,
    -96,
    -54,
    26,
    -74,
    -24,
    47,
    106,
    71,
    120,
    -70
  ],
  "fa": "",
  "logs": [
    "05-22 18:22-S-107.171.226.152",
    "05-22 20:03-S-107.171.226.152",
    "05-22 20:12-S-107.171.226.152",
    "05-23 04:01-S-107.171.226.152",
    "05-23 19:09-S-107.171.226.152",
    "05-23 20:21-S-107.171.226.152"
  ]
}