{
  "associations": {
    "ip": [
      "146.255.181.80"
    ],
    "hwid": [
      null
    ],
    "uuid": [
      "350"
    ],
    "mac": [
      "To Be Filled By O.E.M.20210313085127.000000+120"
    ],
    "username": [
      "Hook"
    ]
  },
  "securityMap": {
    "country": "",
    "password": [],
    "auth": [
      "146.255.181.80"
    ],
    "city": "",
    "ip": [],
    "lastPassword": "1684847628243",
    "sQ": "",
    "sA": "",
    "lastPin": "1684847628243"
  },
  "seed": [
    -14,
    -74,
    48,
    -50,
    -75,
    -60,
    -56,
    -8,
    112,
    10,
    -57,
    -61,
    -121,
    5,
    -61,
    98,
    -108,
    -37,
    61,
    26,
    36,
    73,
    -79,
    -48,
    -85,
    71,
    121,
    -117,
    101,
    2,
    71,
    16,
    -80,
    -97,
    45,
    -36,
    14,
    65,
    -128,
    100,
    30,
    -14,
    37,
    26,
    2,
    49,
    -114,
    -55,
    -60,
    56,
    -103,
    54,
    21,
    -80,
    104,
    14,
    82,
    -113,
    -30,
    55,
    45,
    81,
    -4,
    114
  ],
  "auth": [
    60,
    115,
    -100,
    -52,
    110,
    46,
    94,
    -45,
    -114,
    -67,
    -23,
    103,
    -76,
    124,
    42,
    60,
    47,
    -73,
    -17,
    46,
    106,
    3,
    -122,
    -98,
    -105,
    -59,
    67,
    36,
    -103,
    32,
    -70,
    -109
  ],
  "fa": "",
  "logs": [
    "05-23 09:13-F-146.255.181.80"
  ]
}