{
  "associations": {
    "auth": [
      "70.54.163.158"
    ],
    "ip": [
      "70.54.163.158"
    ],
    "hwid": [
      "FBB97A6D-2F10-D0D1-5B93-244BFE898318"
    ],
    "uuid": [
      "350"
    ],
    "mac": [
      "24-4B-FE-89-83-18"
    ],
    "username": [
      "New Wind"
    ]
  },
  "securityMap": {
    "country": "",
    "password": [],
    "auth": [
      "70.54.163.158"
    ],
    "city": "",
    "ip": [],
    "hwid": [
      "FBB97A6D-2F10-D0D1-5B93-244BFE898318"
    ],
    "lastPassword": "1684894494463",
    "sQ": "",
    "sA": "",
    "lastPin": "1684894494463"
  },
  "seed": [
    80,
    93,
    78,
    -67,
    84,
    35,
    -45,
    -53,
    88,
    -46,
    -63,
    -120,
    25,
    22,
    25,
    92,
    110,
    -62,
    81,
    -54,
    125,
    36,
    43,
    -23,
    -63,
    -118,
    74,
    -54,
    -1,
    -101,
    -109,
    15,
    -22,
    -103,
    50,
    68,
    -16,
    76,
    -29,
    85,
    -93,
    -100,
    -118,
    42,
    127,
    -10,
    -117,
    -31,
    53,
    17,
    55,
    83,
    78,
    -38,
    -55,
    79,
    28,
    -76,
    -80,
    -121,
    39,
    -106,
    -107,
    -64
  ],
  "auth": [
    -72,
    91,
    100,
    -91,
    49,
    45,
    19,
    -126,
    -3,
    -18,
    -14,
    -17,
    75,
    -88,
    91,
    -80,
    -100,
    -109,
    14,
    85,
    -6,
    -43,
    8,
    95,
    -125,
    58,
    -124,
    -35,
    -113,
    -9,
    -40,
    47
  ],
  "fa": "",
  "logs": [
    "05-23 22:14-S-70.54.163.158"
  ]
}