{
  "shop": [
    {
      "id": 922,
      "amount": 1,
      "maxAmount": 1,
      "price": 25000,
      "effect": "NOTHING",
      "bonus": 0
    },
    {
      "id": 777,
      "amount": 1,
      "maxAmount": 1,
      "price": 25000,
      "effect": "NOTHING",
      "bonus": 0
    },
    {
      "id": 931,
      "amount": 1,
      "maxAmount": 1,
      "price": 25000,
      "effect": "NOTHING",
      "bonus": 0
    },
    null,
    null,
    null,
    null,
    null,
    null,
    null,
    null,
    null,
    null,
    null,
    null,
    null,
    null,
    null,
    null,
    null,
    null,
    null,
    null,
    null,
    null,
    null,
    null,
    null,
    null,
    null,
    null,
    null
  ],
  "earnings": 147000
}