{
  "shop-history": [
    {
      "id": 10946,
      "amount": 4,
      "buyer": "Like My Peep",
      "price": 50000,
      "effect": "NOTHING",
      "bonus": 0
    },
    {
      "id": 23049,
      "amount": 1,
      "buyer": "Netflix",
      "price": 200000,
      "effect": "NOTHING",
      "bonus": 0
    },
    {
      "id": 10946,
      "amount": 15,
      "buyer": "Slayerfly",
      "price": 30000,
      "effect": "NOTHING",
      "bonus": 0
    },
    {
      "id": 10946,
      "amount": 10,
      "buyer": "Suh",
      "price": 35000,
      "effect": "NOTHING",
      "bonus": 0
    },
    {
      "id": 10946,
      "amount": 10,
      "buyer": "Suh",
      "price": 35000,
      "effect": "NOTHING",
      "bonus": 0
    },
    {
      "id": 23057,
      "amount": 5,
      "buyer": "Suh",
      "price": 400000,
      "effect": "NOTHING",
      "bonus": 0
    }
  ]
}