{
  "total-play-time-ms": 276697520,
  "username": "Cheech",
  "password": "omfgomfgomfg",
  "email": "null",
  "staff-rights": "TORMENTED_DONATOR",
  "game-mode": "NORMAL",
  "loyalty-title": "NONE",
  "yellhexcolor": "ffffff",
  "position": {
    "x": 2981,
    "y": 2772,
    "z": 0
  },
  "online-status": "ON",
  "given-starter": true,
  "has-pin2": true,
  "saved-pin2": "4217",
  "saved-ip": "223.252.16.134",
  "donated": 250,
  "current-boss-task": 0,
  "current-boss-amount": 0,
  "global-rate": 0,
  "peng-rate": 0,
  "slayer-rate": 0,
  "has-completed-boss-task": false,
  "current-daily-task-amount": 0,
  "current-daily-task-x-pos": 0,
  "current-daily-task-y-pos": 0,
  "current-daily-task-z-pos": 0,
  "current-daily-task-reward": 0,
  "uim-bank": {},
  "dg-floor": 0,
  "dg-prestige": 0,
  "clue-task": "NO_TASK",
  "clue-kc": 0,
  "daysVoted": 0,
  "totalTimesClaimed": 0,
  "longestDaysVoted": 0,
  "timeUntilNextReward": 0,
  "current-voting-streak": 0,
  "entriesCurrency": 0.0,
  "amount-donated-today": 240,
  "claimed-first": false,
  "claimed-second": false,
  "claimed-third": false,
  "last-donation": 0,
  "last-time-reset": 0,
  "is-secondary-equipment": false,
  "lastlogin": 1682235586023,
  "lastdailyclaim": 0,
  "lastvotetime": 0,
  "hasvotedtoday": false,
  "day1claimed": false,
  "day2claimed": false,
  "day3claimed": false,
  "day4claimed": false,
  "day5claimed": false,
  "day6claimed": false,
  "day7claimed": false,
  "minutes-bonus-exp": 2227,
  "minutes-voting-dr": -1,
  "minutes-voting-dmg": 0,
  "total-gained-exp": -736346221,
  "barrows-points": 0,
  "donator-points": 40,
  "Skilling-points": 0,
  "prestige-points": 0,
  "achievement-points": 0,
  "dung-tokens": 0,
  "commendations": 0,
  "loyalty-points": 0,
  "total-loyalty-points": 0.0,
  "godmodetime": 0,
  "voting-points": 1,
  "tasks-completion": [
    false,
    false,
    false,
    true,
    true,
    false
  ],
  "tasks-progress": [
    999,
    0,
    0,
    0,
    0,
    0,
    0,
    0,
    0,
    0,
    0,
    0,
    0,
    0,
    0,
    0,
    0,
    0,
    0,
    0,
    0,
    0,
    0,
    0,
    0,
    0,
    0,
    0,
    0,
    0,
    0,
    0,
    0,
    0,
    0,
    0,
    0,
    0,
    0,
    0,
    0,
    0,
    0,
    0,
    0,
    0,
    0,
    0,
    0,
    0,
    0,
    0,
    0,
    0,
    0
  ],
  "total-prestiges": 0,
  "slayer-spree": 111,
  "npc-killcount": 52270,
  "spawn-killcount": 0,
  "lord-killcount": 0,
  "demon-killcount": 369,
  "dragon-killcount": 0,
  "beast-killcount": 0,
  "king-killcount": 0,
  "avatar-killcount": 106,
  "angel-killcount": 0,
  "lucien-killcount": 0,
  "hercules-killcount": 0,
  "satan-killcount": 313,
  "zeus-killcount": 0,
  "mini-lucifer-killcount": 0,
  "lucifer-killcount": 0,
  "event-points": 0,
  "boss-points": 0,
  "shilling-rate": 0,
  "slayer-points": 0,
  "pk-points": 0,
  "player-kills": 0,
  "player-killstreak": 0,
  "player-deaths": 0,
  "target-percentage": 0,
  "bh-rank": -1,
  "gender": "MALE",
  "spell-book": "NORMAL",
  "prayer-book": "CURSES",
  "running": true,
  "run-energy": 100,
  "music": false,
  "sounds": true,
  "auto-retaliate": true,
  "xp-locked": false,
  "veng-cast": false,
  "last-veng": 1682181517611,
  "fight-type": "STAFF_POUND",
  "sol-effect": 0,
  "skull-timer": 0,
  "fuse-combination-timer": 0,
  "fuse-item-selected": 0,
  "claimed-fuse-item": true,
  "fuse-in-progress": false,
  "accept-aid": false,
  "poison-damage": 0,
  "poison-immunity": 0,
  "overload-timer": 0,
  "aggro-timer": 0,
  "exp-timer": 0,
  "dr-timer": 0,
  "ddr-timer": 0,
  "dmg-timer": 0,
  "double-dr-timer": 0,
  "double-ddr-timer": 0,
  "double-dmg-timer": 0,
  "fire-immunity": 0,
  "fire-damage-mod": 0,
  "prayer-renewal-timer": 0,
  "teleblock-timer": 0,
  "special-amount": 100,
  "entered-gwd-room": false,
  "gwd-altar-delay": 0,
  "gwd-killcount": [
    0,
    0,
    0,
    0
  ],
  "effigy": 0,
  "summon-npc": 3039,
  "summon-death": -1,
  "process-farming": false,
  "clanchat": "Help",
  "autocast": false,
  "autocast-spell": 1154,
  "dfs-charges": 0,
  "coins-gambled": 0,
  "slayer-master": "BOSS_SLAYER",
  "slayer-task": "GORVEK",
  "prev-slayer-task": "ONYX_GRIFFIN",
  "task-amount": 50,
  "task-streak": 95,
  "duo-partner": "null",
  "double-slay-xp": false,
  "recoil-deg": 0,
  "blowpipe-deg": 0,
  "brawlers-deg": [
    0,
    0,
    0,
    0,
    0,
    0,
    0,
    0,
    0,
    0,
    0
  ],
  "ancient-deg": [
    0,
    0,
    0,
    0,
    0,
    0,
    0,
    0,
    0,
    0,
    0,
    0,
    0,
    0,
    0
  ],
  "killed-players": [],
  "killed-gods": [
    false,
    false,
    false,
    false,
    false
  ],
  "vod-brother": [
    [
      9029,
      0
    ],
    [
      9028,
      0
    ],
    [
      9030,
      0
    ]
  ],
  "vod-killcount": 0,
  "hov-killcount": 0,
  "barrows-brother": [
    [
      2030,
      0
    ],
    [
      2029,
      0
    ],
    [
      2028,
      0
    ],
    [
      2027,
      0
    ],
    [
      2026,
      0
    ],
    [
      2025,
      0
    ]
  ],
  "random-coffin": 0,
  "barrows-killcount": 0,
  "nomad": [
    false,
    false
  ],
  "recipe-for-disaster": [
    false,
    false,
    false,
    false,
    false,
    false,
    false,
    false,
    false
  ],
  "recipe-for-disaster-wave": 0,
  "clue-progress": 0,
  "dung-items-bound": [
    0,
    0,
    0,
    0,
    0
  ],
  "collection-data": [
    {
      "npcId": 9837,
      "item": 995,
      "amount": 109
    },
    {
      "npcId": 9837,
      "item": 2023,
      "amount": 10
    },
    {
      "npcId": 9027,
      "item": 995,
      "amount": 220
    },
    {
      "npcId": 9027,
      "item": 2023,
      "amount": 21
    },
    {
      "npcId": 9027,
      "item": 19985,
      "amount": 1
    },
    {
      "npcId": 9027,
      "item": 19984,
      "amount": 1
    },
    {
      "npcId": 9835,
      "item": 995,
      "amount": 329
    },
    {
      "npcId": 9835,
      "item": 2023,
      "amount": 30
    },
    {
      "npcId": 9911,
      "item": 995,
      "amount": 441
    },
    {
      "npcId": 9911,
      "item": 2023,
      "amount": 42
    },
    {
      "npcId": 9911,
      "item": 20400,
      "amount": 1
    },
    {
      "npcId": 9922,
      "item": 995,
      "amount": 574
    },
    {
      "npcId": 9922,
      "item": 2023,
      "amount": 75
    },
    {
      "npcId": 9922,
      "item": 19989,
      "amount": 1
    },
    {
      "npcId": 9838,
      "item": 995,
      "amount": 663
    },
    {
      "npcId": 9838,
      "item": 2023,
      "amount": 64
    },
    {
      "npcId": 9838,
      "item": 20091,
      "amount": 2
    },
    {
      "npcId": 9838,
      "item": 20093,
      "amount": 1
    },
    {
      "npcId": 9838,
      "item": 20087,
      "amount": 1
    },
    {
      "npcId": 9838,
      "item": 14487,
      "amount": 1
    },
    {
      "npcId": 9838,
      "item": 20092,
      "amount": 1
    },
    {
      "npcId": 9845,
      "item": 995,
      "amount": 817
    },
    {
      "npcId": 9845,
      "item": 2023,
      "amount": 125
    },
    {
      "npcId": 9845,
      "item": 20087,
      "amount": 1
    },
    {
      "npcId": 9845,
      "item": 20086,
      "amount": 2
    },
    {
      "npcId": 9845,
      "item": 20089,
      "amount": 1
    },
    {
      "npcId": 9845,
      "item": 14487,
      "amount": 3
    },
    {
      "npcId": 9845,
      "item": 20093,
      "amount": 2
    },
    {
      "npcId": 9910,
      "item": 995,
      "amount": 899
    },
    {
      "npcId": 9910,
      "item": 2023,
      "amount": 105
    },
    {
      "npcId": 9910,
      "item": 20087,
      "amount": 1
    },
    {
      "npcId": 9910,
      "item": 20091,
      "amount": 2
    },
    {
      "npcId": 9910,
      "item": 14487,
      "amount": 4
    },
    {
      "npcId": 9910,
      "item": 20089,
      "amount": 1
    },
    {
      "npcId": 9910,
      "item": 20086,
      "amount": 1
    },
    {
      "npcId": 9910,
      "item": 20088,
      "amount": 2
    },
    {
      "npcId": 9807,
      "item": 995,
      "amount": 990
    },
    {
      "npcId": 9807,
      "item": 2023,
      "amount": 91
    },
    {
      "npcId": 9807,
      "item": 20093,
      "amount": 2
    },
    {
      "npcId": 9807,
      "item": 14487,
      "amount": 3
    },
    {
      "npcId": 9807,
      "item": 20087,
      "amount": 1
    },
    {
      "npcId": 9807,
      "item": 20086,
      "amount": 1
    },
    {
      "npcId": 9807,
      "item": 20092,
      "amount": 1
    },
    {
      "npcId": 8013,
      "item": 10946,
      "amount": 56
    },
    {
      "npcId": 8013,
      "item": 23020,
      "amount": 52
    },
    {
      "npcId": 9906,
      "item": 995,
      "amount": 1923677
    },
    {
      "npcId": 9906,
      "item": 2023,
      "amount": 142
    },
    {
      "npcId": 9904,
      "item": 995,
      "amount": 3045206
    },
    {
      "npcId": 9904,
      "item": 2023,
      "amount": 98
    },
    {
      "npcId": 9807,
      "item": 20091,
      "amount": 1
    },
    {
      "npcId": 6692,
      "item": 995,
      "amount": 1292
    },
    {
      "npcId": 6692,
      "item": 2023,
      "amount": 295
    },
    {
      "npcId": 6692,
      "item": 18003,
      "amount": 7
    },
    {
      "npcId": 6692,
      "item": 18009,
      "amount": 6
    },
    {
      "npcId": 6692,
      "item": 17999,
      "amount": 6
    },
    {
      "npcId": 6692,
      "item": 18011,
      "amount": 4
    },
    {
      "npcId": 6692,
      "item": 18005,
      "amount": 3
    },
    {
      "npcId": 6692,
      "item": 18001,
      "amount": 3
    },
    {
      "npcId": 8014,
      "item": 995,
      "amount": 2439
    },
    {
      "npcId": 8014,
      "item": 2023,
      "amount": 428
    },
    {
      "npcId": 8014,
      "item": 23056,
      "amount": 3
    },
    {
      "npcId": 8014,
      "item": 23051,
      "amount": 2
    },
    {
      "npcId": 8014,
      "item": 23054,
      "amount": 3
    },
    {
      "npcId": 8003,
      "item": 995,
      "amount": 3317
    },
    {
      "npcId": 8003,
      "item": 2023,
      "amount": 320
    },
    {
      "npcId": 8003,
      "item": 8334,
      "amount": 2
    },
    {
      "npcId": 8003,
      "item": 19892,
      "amount": 2
    },
    {
      "npcId": 8003,
      "item": 20594,
      "amount": 1
    },
    {
      "npcId": 202,
      "item": 995,
      "amount": 4403
    },
    {
      "npcId": 202,
      "item": 2023,
      "amount": 422
    },
    {
      "npcId": 202,
      "item": 13306,
      "amount": 1
    },
    {
      "npcId": 9845,
      "item": 20091,
      "amount": 3
    },
    {
      "npcId": 202,
      "item": 13301,
      "amount": 1
    },
    {
      "npcId": 202,
      "item": 13302,
      "amount": 1
    },
    {
      "npcId": 9908,
      "item": 10946,
      "amount": 27
    },
    {
      "npcId": 9908,
      "item": 2023,
      "amount": 327
    },
    {
      "npcId": 8003,
      "item": 8335,
      "amount": 1
    },
    {
      "npcId": 811,
      "item": 995,
      "amount": 5437
    },
    {
      "npcId": 811,
      "item": 2023,
      "amount": 439
    },
    {
      "npcId": 811,
      "item": 21062,
      "amount": 2
    },
    {
      "npcId": 811,
      "item": 21066,
      "amount": 1
    },
    {
      "npcId": 811,
      "item": 21071,
      "amount": 3
    },
    {
      "npcId": 811,
      "item": 21067,
      "amount": 2
    },
    {
      "npcId": 9815,
      "item": 995,
      "amount": 6514
    },
    {
      "npcId": 9815,
      "item": 2023,
      "amount": 519
    },
    {
      "npcId": 9907,
      "item": 10946,
      "amount": 44
    },
    {
      "npcId": 9907,
      "item": 2023,
      "amount": 143
    },
    {
      "npcId": 9815,
      "item": 21049,
      "amount": 1
    },
    {
      "npcId": 9815,
      "item": 21040,
      "amount": 2
    },
    {
      "npcId": 9815,
      "item": 21038,
      "amount": 1
    },
    {
      "npcId": 9815,
      "item": 21048,
      "amount": 1
    },
    {
      "npcId": 9817,
      "item": 995,
      "amount": 7472
    },
    {
      "npcId": 9817,
      "item": 2023,
      "amount": 474
    },
    {
      "npcId": 9817,
      "item": 17664,
      "amount": 1
    },
    {
      "npcId": 9817,
      "item": 23138,
      "amount": 1
    },
    {
      "npcId": 9817,
      "item": 23137,
      "amount": 1
    },
    {
      "npcId": 9920,
      "item": 995,
      "amount": 8550
    },
    {
      "npcId": 9920,
      "item": 2023,
      "amount": 540
    },
    {
      "npcId": 8014,
      "item": 23055,
      "amount": 1
    },
    {
      "npcId": 8014,
      "item": 23052,
      "amount": 1
    },
    {
      "npcId": 8014,
      "item": 23050,
      "amount": 1
    },
    {
      "npcId": 9920,
      "item": 14915,
      "amount": 1
    },
    {
      "npcId": 9920,
      "item": 14910,
      "amount": 1
    },
    {
      "npcId": 9920,
      "item": 14911,
      "amount": 1
    },
    {
      "npcId": 3831,
      "item": 995,
      "amount": 9871
    },
    {
      "npcId": 3831,
      "item": 2023,
      "amount": 850
    },
    {
      "npcId": 3831,
      "item": 14733,
      "amount": 1
    },
    {
      "npcId": 3831,
      "item": 14377,
      "amount": 1
    },
    {
      "npcId": 3831,
      "item": 10865,
      "amount": 1
    },
    {
      "npcId": 3831,
      "item": 12864,
      "amount": 2
    },
    {
      "npcId": 9025,
      "item": 995,
      "amount": 10876
    },
    {
      "npcId": 9025,
      "item": 2023,
      "amount": 880
    },
    {
      "npcId": 9025,
      "item": 8818,
      "amount": 2
    },
    {
      "npcId": 9025,
      "item": 8817,
      "amount": 1
    },
    {
      "npcId": 9026,
      "item": 995,
      "amount": 11159
    },
    {
      "npcId": 9026,
      "item": 2023,
      "amount": 155
    },
    {
      "npcId": 3831,
      "item": 14732,
      "amount": 2
    },
    {
      "npcId": 9025,
      "item": 8816,
      "amount": 1
    },
    {
      "npcId": 9025,
      "item": 8819,
      "amount": 1
    },
    {
      "npcId": 3831,
      "item": 14734,
      "amount": 1
    },
    {
      "npcId": 202,
      "item": 18683,
      "amount": 1
    },
    {
      "npcId": 9914,
      "item": 995,
      "amount": 24466
    },
    {
      "npcId": 9914,
      "item": 2023,
      "amount": 1466
    },
    {
      "npcId": 9918,
      "item": 995,
      "amount": 21492
    },
    {
      "npcId": 9918,
      "item": 2023,
      "amount": 496
    },
    {
      "npcId": 9024,
      "item": 995,
      "amount": 19860
    },
    {
      "npcId": 9024,
      "item": 2023,
      "amount": 858
    },
    {
      "npcId": 9024,
      "item": 11183,
      "amount": 2
    },
    {
      "npcId": 2342,
      "item": 995,
      "amount": 18309
    },
    {
      "npcId": 2342,
      "item": 2023,
      "amount": 298
    },
    {
      "npcId": 8002,
      "item": 995,
      "amount": 29303
    },
    {
      "npcId": 8010,
      "item": 995,
      "amount": 36558
    },
    {
      "npcId": 9839,
      "item": 995,
      "amount": 26129
    },
    {
      "npcId": 3014,
      "item": 995,
      "amount": 34399
    },
    {
      "npcId": 3013,
      "item": 995,
      "amount": 33426
    },
    {
      "npcId": 9903,
      "item": 995,
      "amount": 28827
    },
    {
      "npcId": 9806,
      "item": 995,
      "amount": 28383
    },
    {
      "npcId": 3010,
      "item": 995,
      "amount": 31895
    },
    {
      "npcId": 9017,
      "item": 995,
      "amount": 31163
    },
    {
      "npcId": 9816,
      "item": 995,
      "amount": 28083
    },
    {
      "npcId": 1746,
      "item": 995,
      "amount": 31486
    },
    {
      "npcId": 9915,
      "item": 995,
      "amount": 17497
    },
    {
      "npcId": 9915,
      "item": 2023,
      "amount": 498
    },
    {
      "npcId": 8008,
      "item": 995,
      "amount": 15211
    },
    {
      "npcId": 8008,
      "item": 2023,
      "amount": 212
    },
    {
      "npcId": 9914,
      "item": 22122,
      "amount": 1
    },
    {
      "npcId": 9916,
      "item": 995,
      "amount": 20157
    },
    {
      "npcId": 9916,
      "item": 2023,
      "amount": 158
    },
    {
      "npcId": 9024,
      "item": 11184,
      "amount": 1
    },
    {
      "npcId": 9918,
      "item": 17391,
      "amount": 1
    },
    {
      "npcId": 9915,
      "item": 14051,
      "amount": 1
    },
    {
      "npcId": 9915,
      "item": 14052,
      "amount": 2
    },
    {
      "npcId": 9914,
      "item": 22126,
      "amount": 1
    },
    {
      "npcId": 3010,
      "item": 16194,
      "amount": 2
    },
    {
      "npcId": 9017,
      "item": 15646,
      "amount": 4
    },
    {
      "npcId": 8013,
      "item": 2736,
      "amount": 8
    },
    {
      "npcId": 3014,
      "item": 19489,
      "amount": 2
    },
    {
      "npcId": 9017,
      "item": 22135,
      "amount": 2
    },
    {
      "npcId": 9017,
      "item": 15645,
      "amount": 1
    },
    {
      "npcId": 3016,
      "item": 995,
      "amount": 70218
    }
  ],
  "holy-prayers-unlocked": [
    false,
    false,
    false,
    false,
    false,
    false
  ],
  "rune-ess": 0,
  "pure-ess": 0,
  "has-bank-pin": false,
  "last-pin-attempt": 0,
  "invalid-pin-attempts": 0,
  "bank-pin": [
    0,
    0,
    0,
    0
  ],
  "appearance": [
    0,
    1,
    18,
    26,
    33,
    40,
    42,
    10,
    11,
    1,
    4,
    0,
    1
  ],
  "agility-obj": [
    false,
    false,
    false,
    false,
    false,
    false,
    false
  ],
  "skills": {
    "level": [
      120,
      120,
      120,
      1200,
      120,
      0,
      120,
      1,
      1,
      1,
      1,
      1,
      120,
      1,
      120,
      92,
      1,
      1,
      116,
      1,
      1,
      90,
      1,
      1,
      1
    ],
    "maxLevel": [
      120,
      120,
      120,
      1200,
      120,
      1200,
      120,
      1,
      1,
      1,
      1,
      1,
      120,
      1,
      120,
      92,
      1,
      1,
      116,
      1,
      1,
      90,
      1,
      1,
      1
    ],
    "experience": [
      2000000000,
      106951223,
      2000000000,
      2000000000,
      1387557397,
      2000000000,
      2000000000,
      0,
      0,
      0,
      0,
      0,
      114747360,
      0,
      407561315,
      6626678,
      0,
      0,
      77161325,
      0,
      0,
      5737030,
      0,
      0,
      0
    ]
  },
  "inventory": [
    {
      "id": 21815,
      "amount": 2,
      "slot": 0,
      "bonus": {
        "effect": "NOTHING",
        "rarity": "COMMON",
        "bonus": 0
      }
    },
    {
      "id": 23178,
      "amount": 1,
      "slot": 0,
      "bonus": {
        "effect": "NOTHING",
        "rarity": "COMMON",
        "bonus": 0
      }
    },
    {
      "id": 23174,
      "amount": 1,
      "slot": 0,
      "bonus": {
        "effect": "NOTHING",
        "rarity": "COMMON",
        "bonus": 0
      }
    },
    {
      "id": 10835,
      "amount": 7093279,
      "slot": 0,
      "bonus": {
        "effect": "NOTHING",
        "rarity": "COMMON",
        "bonus": 0
      }
    },
    {
      "id": 995,
      "amount": 4270072,
      "slot": 0,
      "bonus": {
        "effect": "NOTHING",
        "rarity": "COMMON",
        "bonus": 0
      }
    },
    {
      "id": 2023,
      "amount": 1310,
      "slot": 0,
      "bonus": {
        "effect": "NOTHING",
        "rarity": "COMMON",
        "bonus": 0
      }
    },
    {
      "id": 11137,
      "amount": 2,
      "slot": 0,
      "bonus": {
        "effect": "NOTHING",
        "rarity": "COMMON",
        "bonus": 0
      }
    },
    {
      "id": 5023,
      "amount": 134,
      "slot": 0,
      "bonus": {
        "effect": "NOTHING",
        "rarity": "COMMON",
        "bonus": 0
      }
    },
    {
      "id": 10946,
      "amount": 10,
      "slot": 0,
      "bonus": {
        "effect": "NOTHING",
        "rarity": "COMMON",
        "bonus": 0
      }
    },
    {
      "id": 23020,
      "amount": 3,
      "slot": 0,
      "bonus": {
        "effect": "NOTHING",
        "rarity": "COMMON",
        "bonus": 0
      }
    },
    {
      "id": 20552,
      "amount": 1,
      "slot": 0,
      "bonus": {
        "effect": "NOTHING",
        "rarity": "COMMON",
        "bonus": 0
      }
    },
    {
      "id": -1,
      "amount": 0,
      "slot": 0,
      "bonus": {
        "effect": "NOTHING",
        "rarity": "COMMON",
        "bonus": 0
      }
    },
    {
      "id": -1,
      "amount": 0,
      "slot": 0,
      "bonus": {
        "effect": "NOTHING",
        "rarity": "COMMON",
        "bonus": 0
      }
    },
    {
      "id": -1,
      "amount": 0,
      "slot": 0,
      "bonus": {
        "effect": "NOTHING",
        "rarity": "COMMON",
        "bonus": 0
      }
    },
    {
      "id": -1,
      "amount": 0,
      "slot": 0,
      "bonus": {
        "effect": "NOTHING",
        "rarity": "COMMON",
        "bonus": 0
      }
    },
    {
      "id": -1,
      "amount": 0,
      "slot": 0,
      "bonus": {
        "effect": "NOTHING",
        "rarity": "COMMON",
        "bonus": 0
      }
    },
    {
      "id": -1,
      "amount": 0,
      "slot": 0,
      "bonus": {
        "effect": "NOTHING",
        "rarity": "COMMON",
        "bonus": 0
      }
    },
    {
      "id": -1,
      "amount": 0,
      "slot": 0,
      "bonus": {
        "effect": "NOTHING",
        "rarity": "COMMON",
        "bonus": 0
      }
    },
    {
      "id": -1,
      "amount": 0,
      "slot": 0,
      "bonus": {
        "effect": "NOTHING",
        "rarity": "COMMON",
        "bonus": 0
      }
    },
    {
      "id": -1,
      "amount": 0,
      "slot": 0,
      "bonus": {
        "effect": "NOTHING",
        "rarity": "COMMON",
        "bonus": 0
      }
    },
    {
      "id": -1,
      "amount": 0,
      "slot": 0,
      "bonus": {
        "effect": "NOTHING",
        "rarity": "COMMON",
        "bonus": 0
      }
    },
    {
      "id": -1,
      "amount": 0,
      "slot": 0,
      "bonus": {
        "effect": "NOTHING",
        "rarity": "COMMON",
        "bonus": 0
      }
    },
    {
      "id": -1,
      "amount": 0,
      "slot": 0,
      "bonus": {
        "effect": "NOTHING",
        "rarity": "COMMON",
        "bonus": 0
      }
    },
    {
      "id": -1,
      "amount": 0,
      "slot": 0,
      "bonus": {
        "effect": "NOTHING",
        "rarity": "COMMON",
        "bonus": 0
      }
    },
    {
      "id": 23125,
      "amount": 1,
      "slot": 0
    },
    {
      "id": 23122,
      "amount": 1,
      "slot": 0,
      "bonus": {
        "effect": "NOTHING",
        "rarity": "COMMON",
        "bonus": 0
      }
    },
    {
      "id": -1,
      "amount": 0,
      "slot": 0,
      "bonus": {
        "effect": "NOTHING",
        "rarity": "COMMON",
        "bonus": 0
      }
    },
    {
      "id": -1,
      "amount": 0,
      "slot": 0,
      "bonus": {
        "effect": "NOTHING",
        "rarity": "COMMON",
        "bonus": 0
      }
    }
  ],
  "equipment": [
    {
      "id": 15005,
      "amount": 1,
      "slot": 0,
      "bonus": {
        "effect": "NOTHING",
        "rarity": "COMMON",
        "bonus": 0
      }
    },
    {
      "id": 15100,
      "amount": 1,
      "slot": 0,
      "bonus": {
        "effect": "TRIPLE_KILLS",
        "rarity": "MYTHIC",
        "bonus": 2
      }
    },
    {
      "id": 19886,
      "amount": 1,
      "slot": 0,
      "bonus": {
        "effect": "NOTHING",
        "rarity": "COMMON",
        "bonus": 0
      }
    },
    {
      "id": 22143,
      "amount": 1,
      "slot": 0,
      "bonus": {
        "effect": "ALL_DAMAGE_LOW",
        "rarity": "RARE",
        "bonus": 1
      }
    },
    {
      "id": 14178,
      "amount": 1,
      "slot": 0,
      "bonus": {
        "effect": "NOTHING",
        "rarity": "COMMON",
        "bonus": 0
      }
    },
    {
      "id": 15008,
      "amount": 1,
      "slot": 0,
      "bonus": {
        "effect": "NOTHING",
        "rarity": "COMMON",
        "bonus": 0
      }
    },
    {
      "id": 22142,
      "amount": 1,
      "slot": 0,
      "bonus": {
        "effect": "NOTHING",
        "rarity": "COMMON",
        "bonus": 0
      }
    },
    {
      "id": 22138,
      "amount": 1,
      "slot": 0,
      "bonus": {
        "effect": "NOTHING",
        "rarity": "COMMON",
        "bonus": 0
      }
    },
    {
      "id": 17391,
      "amount": 1,
      "slot": 0,
      "bonus": {
        "effect": "NOTHING",
        "rarity": "COMMON",
        "bonus": 0
      }
    },
    {
      "id": 15200,
      "amount": 1,
      "slot": 0,
      "bonus": {
        "effect": "NOTHING",
        "rarity": "COMMON",
        "bonus": 0
      }
    },
    {
      "id": 3107,
      "amount": 1,
      "slot": 0,
      "bonus": {
        "effect": "ALL_DAMAGE_MEDIUM",
        "rarity": "LEGENDARY",
        "bonus": 2
      }
    },
    {
      "id": -1,
      "amount": 0,
      "slot": 0,
      "bonus": {
        "effect": "NOTHING",
        "rarity": "COMMON",
        "bonus": 0
      }
    },
    {
      "id": 23092,
      "amount": 1,
      "slot": 0,
      "bonus": {
        "effect": "ALL_DAMAGE_LOW",
        "rarity": "RARE",
        "bonus": 1
      }
    },
    {
      "id": -1,
      "amount": 0,
      "slot": 0,
      "bonus": {
        "effect": "NOTHING",
        "rarity": "COMMON",
        "bonus": 0
      }
    },
    {
      "id": -1,
      "amount": 0,
      "slot": 0,
      "bonus": {
        "effect": "NOTHING",
        "rarity": "COMMON",
        "bonus": 0
      }
    }
  ],
  "secondary-equipment": [
    {
      "id": -1,
      "amount": 0,
      "slot": 0,
      "bonus": {
        "effect": "NOTHING",
        "rarity": "COMMON",
        "bonus": 0
      }
    },
    {
      "id": -1,
      "amount": 0,
      "slot": 0,
      "bonus": {
        "effect": "NOTHING",
        "rarity": "COMMON",
        "bonus": 0
      }
    },
    {
      "id": -1,
      "amount": 0,
      "slot": 0,
      "bonus": {
        "effect": "NOTHING",
        "rarity": "COMMON",
        "bonus": 0
      }
    },
    {
      "id": -1,
      "amount": 0,
      "slot": 0,
      "bonus": {
        "effect": "NOTHING",
        "rarity": "COMMON",
        "bonus": 0
      }
    },
    {
      "id": -1,
      "amount": 0,
      "slot": 0,
      "bonus": {
        "effect": "NOTHING",
        "rarity": "COMMON",
        "bonus": 0
      }
    },
    {
      "id": -1,
      "amount": 0,
      "slot": 0,
      "bonus": {
        "effect": "NOTHING",
        "rarity": "COMMON",
        "bonus": 0
      }
    },
    {
      "id": -1,
      "amount": 0,
      "slot": 0,
      "bonus": {
        "effect": "NOTHING",
        "rarity": "COMMON",
        "bonus": 0
      }
    },
    {
      "id": -1,
      "amount": 0,
      "slot": 0,
      "bonus": {
        "effect": "NOTHING",
        "rarity": "COMMON",
        "bonus": 0
      }
    },
    {
      "id": -1,
      "amount": 0,
      "slot": 0,
      "bonus": {
        "effect": "NOTHING",
        "rarity": "COMMON",
        "bonus": 0
      }
    },
    {
      "id": -1,
      "amount": 0,
      "slot": 0,
      "bonus": {
        "effect": "NOTHING",
        "rarity": "COMMON",
        "bonus": 0
      }
    },
    {
      "id": -1,
      "amount": 0,
      "slot": 0,
      "bonus": {
        "effect": "NOTHING",
        "rarity": "COMMON",
        "bonus": 0
      }
    },
    {
      "id": -1,
      "amount": 0,
      "slot": 0,
      "bonus": {
        "effect": "NOTHING",
        "rarity": "COMMON",
        "bonus": 0
      }
    },
    {
      "id": -1,
      "amount": 0,
      "slot": 0,
      "bonus": {
        "effect": "NOTHING",
        "rarity": "COMMON",
        "bonus": 0
      }
    },
    {
      "id": -1,
      "amount": 0,
      "slot": 0,
      "bonus": {
        "effect": "NOTHING",
        "rarity": "COMMON",
        "bonus": 0
      }
    },
    {
      "id": -1,
      "amount": 0,
      "slot": 0,
      "bonus": {
        "effect": "NOTHING",
        "rarity": "COMMON",
        "bonus": 0
      }
    }
  ],
  "preset-equipment": [
    {
      "id": -1,
      "amount": 0,
      "slot": 0,
      "bonus": {
        "effect": "NOTHING",
        "rarity": "COMMON",
        "bonus": 0
      }
    },
    {
      "id": -1,
      "amount": 0,
      "slot": 0,
      "bonus": {
        "effect": "NOTHING",
        "rarity": "COMMON",
        "bonus": 0
      }
    },
    {
      "id": -1,
      "amount": 0,
      "slot": 0,
      "bonus": {
        "effect": "NOTHING",
        "rarity": "COMMON",
        "bonus": 0
      }
    },
    {
      "id": -1,
      "amount": 0,
      "slot": 0,
      "bonus": {
        "effect": "NOTHING",
        "rarity": "COMMON",
        "bonus": 0
      }
    },
    {
      "id": -1,
      "amount": 0,
      "slot": 0,
      "bonus": {
        "effect": "NOTHING",
        "rarity": "COMMON",
        "bonus": 0
      }
    },
    {
      "id": -1,
      "amount": 0,
      "slot": 0,
      "bonus": {
        "effect": "NOTHING",
        "rarity": "COMMON",
        "bonus": 0
      }
    },
    {
      "id": -1,
      "amount": 0,
      "slot": 0,
      "bonus": {
        "effect": "NOTHING",
        "rarity": "COMMON",
        "bonus": 0
      }
    },
    {
      "id": -1,
      "amount": 0,
      "slot": 0,
      "bonus": {
        "effect": "NOTHING",
        "rarity": "COMMON",
        "bonus": 0
      }
    },
    {
      "id": -1,
      "amount": 0,
      "slot": 0,
      "bonus": {
        "effect": "NOTHING",
        "rarity": "COMMON",
        "bonus": 0
      }
    },
    {
      "id": -1,
      "amount": 0,
      "slot": 0,
      "bonus": {
        "effect": "NOTHING",
        "rarity": "COMMON",
        "bonus": 0
      }
    },
    {
      "id": -1,
      "amount": 0,
      "slot": 0,
      "bonus": {
        "effect": "NOTHING",
        "rarity": "COMMON",
        "bonus": 0
      }
    },
    {
      "id": -1,
      "amount": 0,
      "slot": 0,
      "bonus": {
        "effect": "NOTHING",
        "rarity": "COMMON",
        "bonus": 0
      }
    },
    {
      "id": -1,
      "amount": 0,
      "slot": 0,
      "bonus": {
        "effect": "NOTHING",
        "rarity": "COMMON",
        "bonus": 0
      }
    },
    {
      "id": -1,
      "amount": 0,
      "slot": 0,
      "bonus": {
        "effect": "NOTHING",
        "rarity": "COMMON",
        "bonus": 0
      }
    },
    {
      "id": -1,
      "amount": 0,
      "slot": 0,
      "bonus": {
        "effect": "NOTHING",
        "rarity": "COMMON",
        "bonus": 0
      }
    }
  ],
  "offences": [],
  "bank-0": [
    {
      "id": 17817,
      "amount": 51,
      "slot": 0,
      "bonus": {
        "effect": "NOTHING",
        "rarity": "COMMON",
        "bonus": 0
      }
    },
    {
      "id": 995,
      "amount": 939,
      "slot": 0,
      "bonus": {
        "effect": "NOTHING",
        "rarity": "COMMON",
        "bonus": 0
      }
    },
    {
      "id": 2023,
      "amount": 0,
      "slot": 0,
      "bonus": {
        "effect": "NOTHING",
        "rarity": "COMMON",
        "bonus": 0
      }
    },
    {
      "id": 3026,
      "amount": 0,
      "slot": 0,
      "bonus": {
        "effect": "NOTHING",
        "rarity": "COMMON",
        "bonus": 0
      }
    },
    {
      "id": 15358,
      "amount": 1,
      "slot": 0,
      "bonus": {
        "effect": "NOTHING",
        "rarity": "COMMON",
        "bonus": 0
      }
    },
    {
      "id": 21815,
      "amount": 0,
      "slot": 0,
      "bonus": {
        "effect": "NOTHING",
        "rarity": "COMMON",
        "bonus": 0
      }
    },
    {
      "id": 10835,
      "amount": 0,
      "slot": 0,
      "bonus": {
        "effect": "NOTHING",
        "rarity": "COMMON",
        "bonus": 0
      }
    },
    {
      "id": 3086,
      "amount": 1,
      "slot": 0,
      "bonus": {
        "effect": "NOTHING",
        "rarity": "COMMON",
        "bonus": 0
      }
    },
    {
      "id": 1033,
      "amount": 1,
      "slot": 0,
      "bonus": {
        "effect": "NOTHING",
        "rarity": "COMMON",
        "bonus": 0
      }
    },
    {
      "id": 3090,
      "amount": 0,
      "slot": 0,
      "bonus": {
        "effect": "NOTHING",
        "rarity": "COMMON",
        "bonus": 0
      }
    },
    {
      "id": 8788,
      "amount": 18,
      "slot": 0,
      "bonus": {
        "effect": "NOTHING",
        "rarity": "COMMON",
        "bonus": 0
      }
    },
    {
      "id": 15359,
      "amount": 1,
      "slot": 0,
      "bonus": {
        "effect": "NOTHING",
        "rarity": "COMMON",
        "bonus": 0
      }
    },
    {
      "id": 23020,
      "amount": 57,
      "slot": 0,
      "bonus": {
        "effect": "NOTHING",
        "rarity": "COMMON",
        "bonus": 0
      }
    },
    {
      "id": 10946,
      "amount": 123,
      "slot": 0,
      "bonus": {
        "effect": "NOTHING",
        "rarity": "COMMON",
        "bonus": 0
      }
    },
    {
      "id": 3030,
      "amount": 4,
      "slot": 0,
      "bonus": {
        "effect": "NOTHING",
        "rarity": "COMMON",
        "bonus": 0
      }
    },
    {
      "id": 1005,
      "amount": 2,
      "slot": 0,
      "bonus": {
        "effect": "NOTHING",
        "rarity": "COMMON",
        "bonus": 0
      }
    },
    {
      "id": 5023,
      "amount": 2143,
      "slot": 0,
      "bonus": {
        "effect": "NOTHING",
        "rarity": "COMMON",
        "bonus": 0
      }
    },
    {
      "id": 942,
      "amount": 2,
      "slot": 0,
      "bonus": {
        "effect": "NOTHING",
        "rarity": "COMMON",
        "bonus": 0
      }
    },
    {
      "id": 229,
      "amount": 48,
      "slot": 0,
      "bonus": {
        "effect": "NOTHING",
        "rarity": "COMMON",
        "bonus": 0
      }
    },
    {
      "id": 4684,
      "amount": 0,
      "slot": 0,
      "bonus": {
        "effect": "NOTHING",
        "rarity": "COMMON",
        "bonus": 0
      }
    },
    {
      "id": 4686,
      "amount": 0,
      "slot": 0,
      "bonus": {
        "effect": "NOTHING",
        "rarity": "COMMON",
        "bonus": 0
      }
    },
    {
      "id": 19481,
      "amount": 1,
      "slot": 0,
      "bonus": {
        "effect": "NOTHING",
        "rarity": "COMMON",
        "bonus": 0
      }
    },
    {
      "id": 13302,
      "amount": 0,
      "slot": 0,
      "bonus": {
        "effect": "DOUBLE_DROP",
        "rarity": "RARE",
        "bonus": 5
      }
    },
    {
      "id": 14911,
      "amount": 0,
      "slot": 0,
      "bonus": {
        "effect": "NOTHING",
        "rarity": "COMMON",
        "bonus": 0
      }
    },
    {
      "id": 783,
      "amount": 3,
      "slot": 0,
      "bonus": {
        "effect": "NOTHING",
        "rarity": "COMMON",
        "bonus": 0
      }
    },
    {
      "id": 17664,
      "amount": 0,
      "slot": 0,
      "bonus": {
        "effect": "NOTHING",
        "rarity": "COMMON",
        "bonus": 0
      }
    },
    {
      "id": 14377,
      "amount": 0,
      "slot": 0,
      "bonus": {
        "effect": "NOTHING",
        "rarity": "COMMON",
        "bonus": 0
      }
    },
    {
      "id": 10865,
      "amount": 0,
      "slot": 0,
      "bonus": {
        "effect": "NOTHING",
        "rarity": "COMMON",
        "bonus": 0
      }
    },
    {
      "id": 23137,
      "amount": 1,
      "slot": 0,
      "bonus": {
        "effect": "DROP_RATE_LOW",
        "rarity": "RARE",
        "bonus": 14
      }
    },
    {
      "id": 14733,
      "amount": 0,
      "slot": 0,
      "bonus": {
        "effect": "RANGE_DAMAGE",
        "rarity": "UNCOMMON",
        "bonus": 1
      }
    },
    {
      "id": 2736,
      "amount": 11,
      "slot": 0,
      "bonus": {
        "effect": "NOTHING",
        "rarity": "COMMON",
        "bonus": 0
      }
    },
    {
      "id": 922,
      "amount": 3,
      "slot": 0,
      "bonus": {
        "effect": "NOTHING",
        "rarity": "COMMON",
        "bonus": 0
      }
    },
    {
      "id": 8819,
      "amount": 0,
      "slot": 0,
      "bonus": {
        "effect": "NOTHING",
        "rarity": "COMMON",
        "bonus": 0
      }
    },
    {
      "id": 21071,
      "amount": 0,
      "slot": 0,
      "bonus": {
        "effect": "ALL_DAMAGE_LOW",
        "rarity": "RARE",
        "bonus": 1
      }
    },
    {
      "id": 14734,
      "amount": 0,
      "slot": 0,
      "bonus": {
        "effect": "NOTHING",
        "rarity": "COMMON",
        "bonus": 0
      }
    },
    {
      "id": 8818,
      "amount": 0,
      "slot": 0,
      "bonus": {
        "effect": "NOTHING",
        "rarity": "COMMON",
        "bonus": 0
      }
    },
    {
      "id": 12864,
      "amount": 0,
      "slot": 0,
      "bonus": {
        "effect": "NOTHING",
        "rarity": "COMMON",
        "bonus": 0
      }
    },
    {
      "id": 11137,
      "amount": 76,
      "slot": 0,
      "bonus": {
        "effect": "NOTHING",
        "rarity": "COMMON",
        "bonus": 0
      }
    },
    {
      "id": 23056,
      "amount": 0,
      "slot": 0,
      "bonus": {
        "effect": "DROP_RATE_LOW",
        "rarity": "RARE",
        "bonus": 6
      }
    },
    {
      "id": 795,
      "amount": 3,
      "slot": 0,
      "bonus": {
        "effect": "NOTHING",
        "rarity": "COMMON",
        "bonus": 0
      }
    },
    {
      "id": 777,
      "amount": 1,
      "slot": 0,
      "bonus": {
        "effect": "NOTHING",
        "rarity": "COMMON",
        "bonus": 0
      }
    },
    {
      "id": 18629,
      "amount": 0,
      "slot": 0,
      "bonus": {
        "effect": "DROP_RATE_LOW",
        "rarity": "RARE",
        "bonus": 17
      }
    },
    {
      "id": 7995,
      "amount": 1,
      "slot": 0,
      "bonus": {
        "effect": "DOUBLE_DROP",
        "rarity": "RARE",
        "bonus": 15
      }
    },
    {
      "id": 19886,
      "amount": 0,
      "slot": 0,
      "bonus": {
        "effect": "NOTHING",
        "rarity": "COMMON",
        "bonus": 0
      }
    },
    {
      "id": 22143,
      "amount": 0,
      "slot": 0,
      "bonus": {
        "effect": "NOTHING",
        "rarity": "COMMON",
        "bonus": 0
      }
    },
    {
      "id": 23051,
      "amount": 1,
      "slot": 0,
      "bonus": {
        "effect": "RANGE_DAMAGE",
        "rarity": "UNCOMMON",
        "bonus": 1
      }
    },
    {
      "id": 14307,
      "amount": 1,
      "slot": 0,
      "bonus": {
        "effect": "NOTHING",
        "rarity": "COMMON",
        "bonus": 0
      }
    },
    {
      "id": 12864,
      "amount": 1,
      "slot": 0,
      "bonus": {
        "effect": "DOUBLE_DROP",
        "rarity": "RARE",
        "bonus": 7
      }
    },
    {
      "id": 23054,
      "amount": 0,
      "slot": 0,
      "bonus": {
        "effect": "DROP_RATE_LOW",
        "rarity": "RARE",
        "bonus": 7
      }
    },
    {
      "id": 8335,
      "amount": 1,
      "slot": 0,
      "bonus": {
        "effect": "NOTHING",
        "rarity": "COMMON",
        "bonus": 0
      }
    },
    {
      "id": 14734,
      "amount": 0,
      "slot": 0,
      "bonus": {
        "effect": "MAGIC_DAMAGE",
        "rarity": "UNCOMMON",
        "bonus": 1
      }
    },
    {
      "id": 916,
      "amount": 2,
      "slot": 0,
      "bonus": {
        "effect": "NOTHING",
        "rarity": "COMMON",
        "bonus": 0
      }
    },
    {
      "id": 5020,
      "amount": 305300,
      "slot": 0,
      "bonus": {
        "effect": "NOTHING",
        "rarity": "COMMON",
        "bonus": 0
      }
    },
    {
      "id": 1351,
      "amount": 1,
      "slot": 0,
      "bonus": {
        "effect": "NOTHING",
        "rarity": "COMMON",
        "bonus": 0
      }
    },
    {
      "id": 1755,
      "amount": 1,
      "slot": 0,
      "bonus": {
        "effect": "NOTHING",
        "rarity": "COMMON",
        "bonus": 0
      }
    },
    {
      "id": 1265,
      "amount": 1,
      "slot": 0,
      "bonus": {
        "effect": "NOTHING",
        "rarity": "COMMON",
        "bonus": 0
      }
    },
    {
      "id": 17634,
      "amount": 910,
      "slot": 0,
      "bonus": {
        "effect": "NOTHING",
        "rarity": "COMMON",
        "bonus": 0
      }
    },
    {
      "id": 919,
      "amount": 3,
      "slot": 0,
      "bonus": {
        "effect": "NOTHING",
        "rarity": "COMMON",
        "bonus": 0
      }
    },
    {
      "id": 928,
      "amount": 1,
      "slot": 0,
      "bonus": {
        "effect": "NOTHING",
        "rarity": "COMMON",
        "bonus": 0
      }
    },
    {
      "id": 789,
      "amount": 2,
      "slot": 0,
      "bonus": {
        "effect": "NOTHING",
        "rarity": "COMMON",
        "bonus": 0
      }
    },
    {
      "id": 10025,
      "amount": 8,
      "slot": 0,
      "bonus": {
        "effect": "NOTHING",
        "rarity": "COMMON",
        "bonus": 0
      }
    },
    {
      "id": 913,
      "amount": 2,
      "slot": 0,
      "bonus": {
        "effect": "NOTHING",
        "rarity": "COMMON",
        "bonus": 0
      }
    },
    {
      "id": 1019,
      "amount": 2,
      "slot": 0,
      "bonus": {
        "effect": "NOTHING",
        "rarity": "COMMON",
        "bonus": 0
      }
    },
    {
      "id": 1023,
      "amount": 1,
      "slot": 0,
      "bonus": {
        "effect": "NOTHING",
        "rarity": "COMMON",
        "bonus": 0
      }
    },
    {
      "id": 1013,
      "amount": 2,
      "slot": 0,
      "bonus": {
        "effect": "NOTHING",
        "rarity": "COMMON",
        "bonus": 0
      }
    },
    {
      "id": 934,
      "amount": 1,
      "slot": 0,
      "bonus": {
        "effect": "NOTHING",
        "rarity": "COMMON",
        "bonus": 0
      }
    },
    {
      "id": 22138,
      "amount": 0,
      "slot": 0,
      "bonus": {
        "effect": "NOTHING",
        "rarity": "COMMON",
        "bonus": 0
      }
    },
    {
      "id": 20095,
      "amount": 1,
      "slot": 0,
      "bonus": {
        "effect": "RANGE_DAMAGE",
        "rarity": "UNCOMMON",
        "bonus": 1
      }
    },
    {
      "id": 20095,
      "amount": 0,
      "slot": 0,
      "bonus": {
        "effect": "NOTHING",
        "rarity": "COMMON",
        "bonus": 0
      }
    },
    {
      "id": 732,
      "amount": 2,
      "slot": 0,
      "bonus": {
        "effect": "NOTHING",
        "rarity": "COMMON",
        "bonus": 0
      }
    },
    {
      "id": 23055,
      "amount": 1,
      "slot": 0,
      "bonus": {
        "effect": "MAGIC_DAMAGE",
        "rarity": "UNCOMMON",
        "bonus": 1
      }
    },
    {
      "id": 925,
      "amount": 1,
      "slot": 0,
      "bonus": {
        "effect": "NOTHING",
        "rarity": "COMMON",
        "bonus": 0
      }
    },
    {
      "id": 1017,
      "amount": 1,
      "slot": 0,
      "bonus": {
        "effect": "NOTHING",
        "rarity": "COMMON",
        "bonus": 0
      }
    },
    {
      "id": 16194,
      "amount": 1,
      "slot": 0,
      "bonus": {
        "effect": "NOTHING",
        "rarity": "COMMON",
        "bonus": 0
      }
    },
    {
      "id": 23037,
      "amount": 1,
      "slot": 0,
      "bonus": {
        "effect": "ALL_DAMAGE_LOW",
        "rarity": "RARE",
        "bonus": 1
      }
    },
    {
      "id": 815,
      "amount": 1,
      "slot": 0,
      "bonus": {
        "effect": "NOTHING",
        "rarity": "COMMON",
        "bonus": 0
      }
    },
    {
      "id": 945,
      "amount": 2,
      "slot": 0,
      "bonus": {
        "effect": "NOTHING",
        "rarity": "COMMON",
        "bonus": 0
      }
    },
    {
      "id": 22122,
      "amount": 0,
      "slot": 0,
      "bonus": {
        "effect": "ALL_DAMAGE_LOW",
        "rarity": "RARE",
        "bonus": 1
      }
    },
    {
      "id": 23135,
      "amount": 1,
      "slot": 0,
      "bonus": {
        "effect": "ALL_DAMAGE_LOW",
        "rarity": "RARE",
        "bonus": 1
      }
    },
    {
      "id": 23058,
      "amount": 0,
      "slot": 0,
      "bonus": {
        "effect": "NOTHING",
        "rarity": "COMMON",
        "bonus": 0
      }
    },
    {
      "id": 23057,
      "amount": 0,
      "slot": 0,
      "bonus": {
        "effect": "NOTHING",
        "rarity": "COMMON",
        "bonus": 0
      }
    },
    {
      "id": 8814,
      "amount": 0,
      "slot": 0,
      "bonus": {
        "effect": "NOTHING",
        "rarity": "COMMON",
        "bonus": 0
      }
    },
    {
      "id": 20095,
      "amount": 0,
      "slot": 0,
      "bonus": {
        "effect": "DOUBLE_DROP",
        "rarity": "RARE",
        "bonus": 6
      }
    },
    {
      "id": 23125,
      "amount": 0,
      "slot": 0,
      "bonus": {
        "effect": "NOTHING",
        "rarity": "COMMON",
        "bonus": 0
      }
    },
    {
      "id": 17616,
      "amount": 1,
      "slot": 0,
      "bonus": {
        "effect": "ALL_DAMAGE_MEDIUM",
        "rarity": "LEGENDARY",
        "bonus": 2
      }
    },
    {
      "id": 22135,
      "amount": 1,
      "slot": 0,
      "bonus": {
        "effect": "NOTHING",
        "rarity": "COMMON",
        "bonus": 0
      }
    },
    {
      "id": 15646,
      "amount": 1,
      "slot": 0,
      "bonus": {
        "effect": "DOUBLE_KILLS",
        "rarity": "LEGENDARY",
        "bonus": 2
      }
    },
    {
      "id": 15645,
      "amount": 1,
      "slot": 0,
      "bonus": {
        "effect": "RANGE_DAMAGE",
        "rarity": "UNCOMMON",
        "bonus": 1
      }
    },
    {
      "id": 22143,
      "amount": 0,
      "slot": 0,
      "bonus": {
        "effect": "ALL_DAMAGE_LOW",
        "rarity": "RARE",
        "bonus": 1
      }
    },
    {
      "id": 20427,
      "amount": 1,
      "slot": 0,
      "bonus": {
        "effect": "TRIPLE_KILLS",
        "rarity": "MYTHIC",
        "bonus": 2
      }
    }
  ],
  "bank-1": [],
  "bank-2": [],
  "bank-3": [],
  "bank-4": [],
  "bank-5": [],
  "bank-6": [],
  "bank-7": [],
  "bank-8": [],
  "new-uim-bank": [],
  "ge-slots": [
    null,
    null,
    null,
    null,
    null,
    null
  ],
  "charm-imp": [
    0,
    0,
    0,
    0
  ],
  "friends": [
    2179735897329160785,
    109725923,
    69277784567898977
  ],
  "ignores": [],
  "loyalty-titles": [
    false,
    false,
    false,
    false,
    false,
    false,
    false,
    false,
    false,
    false,
    false,
    false
  ],
  "kills": [
    {
      "runningTotal": 10614,
      "npcId": 9017,
      "npcName": "Sanctum Golem",
      "amount": 10614,
      "boss": true
    },
    {
      "runningTotal": 3323,
      "npcId": 8010,
      "npcName": "Groudon",
      "amount": 3323,
      "boss": true
    },
    {
      "runningTotal": 1006,
      "npcId": 9903,
      "npcName": "Asmodeus",
      "amount": 1006,
      "boss": true
    },
    {
      "runningTotal": 634,
      "npcId": 3831,
      "npcName": "Zernath",
      "amount": 634,
      "boss": true
    },
    {
      "runningTotal": 375,
      "npcId": 811,
      "npcName": "Nagendra",
      "amount": 375,
      "boss": true
    },
    {
      "runningTotal": 313,
      "npcId": 202,
      "npcName": "Inferno",
      "amount": 313,
      "boss": true
    },
    {
      "runningTotal": 3238,
      "npcId": 9806,
      "npcName": "Gorvek",
      "amount": 3238,
      "boss": false
    },
    {
      "runningTotal": 1936,
      "npcId": 9914,
      "npcName": "Sasuke",
      "amount": 1936,
      "boss": false
    },
    {
      "runningTotal": 1782,
      "npcId": 1746,
      "npcName": "Onyx Griffin",
      "amount": 1782,
      "boss": false
    },
    {
      "runningTotal": 1743,
      "npcId": 3014,
      "npcName": "Lilinryss",
      "amount": 1743,
      "boss": false
    },
    {
      "runningTotal": 1542,
      "npcId": 3013,
      "npcName": "Ag\u0027thomoth",
      "amount": 1542,
      "boss": false
    },
    {
      "runningTotal": 1491,
      "npcId": 9816,
      "npcName": "Dragonite",
      "amount": 1491,
      "boss": false
    },
    {
      "runningTotal": 1445,
      "npcId": 9839,
      "npcName": "Mutant Hydra",
      "amount": 1445,
      "boss": false
    },
    {
      "runningTotal": 1190,
      "npcId": 3010,
      "npcName": "Zeidan Grimm",
      "amount": 1190,
      "boss": false
    },
    {
      "runningTotal": 1185,
      "npcId": 9024,
      "npcName": "Golden Golem",
      "amount": 1185,
      "boss": false
    },
    {
      "runningTotal": 747,
      "npcId": 9915,
      "npcName": "Death God",
      "amount": 747,
      "boss": false
    },
    {
      "runningTotal": 639,
      "npcId": 9918,
      "npcName": "Broly",
      "amount": 639,
      "boss": false
    },
    {
      "runningTotal": 616,
      "npcId": 9025,
      "npcName": "Avalon",
      "amount": 616,
      "boss": false
    },
    {
      "runningTotal": 443,
      "npcId": 9815,
      "npcName": "Kol\u0027gal",
      "amount": 443,
      "boss": false
    },
    {
      "runningTotal": 404,
      "npcId": 9920,
      "npcName": "Ig\u0027thaur",
      "amount": 404,
      "boss": false
    },
    {
      "runningTotal": 369,
      "npcId": 8014,
      "npcName": "Zinqrux",
      "amount": 369,
      "boss": false
    },
    {
      "runningTotal": 364,
      "npcId": 9817,
      "npcName": "Yisdar",
      "amount": 364,
      "boss": false
    },
    {
      "runningTotal": 330,
      "npcId": 2342,
      "npcName": "Emerald Slayer",
      "amount": 330,
      "boss": false
    },
    {
      "runningTotal": 327,
      "npcId": 8002,
      "npcName": "Malvek",
      "amount": 327,
      "boss": false
    },
    {
      "runningTotal": 318,
      "npcId": 8008,
      "npcName": "Avatar titan",
      "amount": 318,
      "boss": false
    },
    {
      "runningTotal": 287,
      "npcId": 6692,
      "npcName": "Revenant Wyvern",
      "amount": 287,
      "boss": false
    },
    {
      "runningTotal": 279,
      "npcId": 8003,
      "npcName": "Dr. Aberrant",
      "amount": 279,
      "boss": false
    },
    {
      "runningTotal": 237,
      "npcId": 9916,
      "npcName": "Luffy",
      "amount": 237,
      "boss": false
    },
    {
      "runningTotal": 114,
      "npcId": 9026,
      "npcName": "Eragon",
      "amount": 114,
      "boss": false
    },
    {
      "runningTotal": 112,
      "npcId": 9845,
      "npcName": "Imperial Scorpion",
      "amount": 112,
      "boss": false
    },
    {
      "runningTotal": 95,
      "npcId": 9910,
      "npcName": "Imperial Ranger",
      "amount": 95,
      "boss": false
    },
    {
      "runningTotal": 91,
      "npcId": 9807,
      "npcName": "Imperial Paladin",
      "amount": 91,
      "boss": false
    },
    {
      "runningTotal": 381,
      "npcId": 3016,
      "npcName": "Varthramoth",
      "amount": 381,
      "boss": false
    },
    {
      "runningTotal": 75,
      "npcId": 9922,
      "npcName": "Blurite Centaur",
      "amount": 75,
      "boss": false
    },
    {
      "runningTotal": 64,
      "npcId": 9838,
      "npcName": "Imperial Hound",
      "amount": 64,
      "boss": false
    },
    {
      "runningTotal": 42,
      "npcId": 9911,
      "npcName": "Blurite Werewolf",
      "amount": 42,
      "boss": false
    },
    {
      "runningTotal": 30,
      "npcId": 9835,
      "npcName": "Blurite Demon",
      "amount": 30,
      "boss": false
    },
    {
      "runningTotal": 21,
      "npcId": 9027,
      "npcName": "Blurite Orc",
      "amount": 21,
      "boss": false
    },
    {
      "runningTotal": 10,
      "npcId": 9837,
      "npcName": "Blurite Goblin",
      "amount": 10,
      "boss": false
    },
    {
      "runningTotal": 0,
      "npcId": 1265,
      "npcName": "Oracle Lion",
      "amount": 0,
      "boss": false
    }
  ],
  "drops": [
    {
      "item": 995,
      "amount": 1565345735,
      "rareDrop": false
    },
    {
      "item": 2023,
      "amount": 25548,
      "rareDrop": false
    },
    {
      "item": 19985,
      "amount": 1,
      "rareDrop": false
    },
    {
      "item": 19984,
      "amount": 1,
      "rareDrop": false
    },
    {
      "item": 20400,
      "amount": 1,
      "rareDrop": false
    },
    {
      "item": 19989,
      "amount": 1,
      "rareDrop": false
    },
    {
      "item": 20091,
      "amount": 2,
      "rareDrop": false
    },
    {
      "item": 20088,
      "amount": 1,
      "rareDrop": false
    },
    {
      "item": 20092,
      "amount": 1,
      "rareDrop": false
    },
    {
      "item": 10946,
      "amount": 335,
      "rareDrop": false
    },
    {
      "item": 23020,
      "amount": 135,
      "rareDrop": false
    },
    {
      "item": 18005,
      "amount": 1,
      "rareDrop": false
    },
    {
      "item": 23056,
      "amount": 1,
      "rareDrop": false
    },
    {
      "item": 23051,
      "amount": 1,
      "rareDrop": false
    },
    {
      "item": 8334,
      "amount": 1,
      "rareDrop": false
    },
    {
      "item": 20594,
      "amount": 1,
      "rareDrop": false
    },
    {
      "item": 21062,
      "amount": 2,
      "rareDrop": false
    },
    {
      "item": 21067,
      "amount": 1,
      "rareDrop": false
    },
    {
      "item": 21040,
      "amount": 2,
      "rareDrop": false
    },
    {
      "item": 23138,
      "amount": 1,
      "rareDrop": false
    },
    {
      "item": 23054,
      "amount": 2,
      "rareDrop": false
    },
    {
      "item": 23050,
      "amount": 1,
      "rareDrop": false
    },
    {
      "item": 14732,
      "amount": 2,
      "rareDrop": false
    },
    {
      "item": 21071,
      "amount": 2,
      "rareDrop": false
    },
    {
      "item": 11183,
      "amount": 2,
      "rareDrop": false
    },
    {
      "item": 14052,
      "amount": 2,
      "rareDrop": false
    },
    {
      "item": 16194,
      "amount": 2,
      "rareDrop": false
    },
    {
      "item": 2736,
      "amount": 20,
      "rareDrop": false
    },
    {
      "item": 19489,
      "amount": 2,
      "rareDrop": false
    }
  ],
  "achievements-completion": [],
  "achievements-progress": [
    0,
    0,
    0,
    0,
    0,
    0,
    0,
    0,
    0,
    0,
    0,
    0,
    0,
    0,
    0,
    0,
    0,
    0,
    0,
    0,
    0,
    0,
    0,
    0,
    0,
    0,
    0,
    0,
    0,
    0,
    0,
    0,
    0,
    0,
    0,
    0,
    0,
    0,
    0,
    0,
    0,
    0,
    0,
    0,
    0,
    0,
    0,
    0,
    0,
    0,
    0,
    0,
    0
  ],
  "fri13may16": false,
  "spiritdebug": false,
  "reffered": false,
  "indung": false,
  "toggledglobalmessages": false,
  "flying": false,
  "canfly": false,
  "ghostwalking": false,
  "canghostwalk": false,
  "barrowschests": 0,
  "cluesteps": 0,
  "difficulty": "MODERN",
  "secondary-equipment-slots-unlocked": [
    false,
    false,
    false,
    false,
    false,
    false,
    false,
    false,
    false,
    false,
    false,
    false,
    false,
    false,
    false
  ],
  "hween2016": [
    false,
    false,
    false,
    false,
    false,
    false,
    false
  ],
  "donehween2016": false,
  "christmas2016": 0,
  "newYear2017": 0,
  "easter2017": 0,
  "hcimdunginventory": [
    {
      "id": -1,
      "amount": 0,
      "slot": 0,
      "bonus": {
        "effect": "NOTHING",
        "rarity": "COMMON",
        "bonus": 0
      }
    },
    {
      "id": -1,
      "amount": 0,
      "slot": 0,
      "bonus": {
        "effect": "NOTHING",
        "rarity": "COMMON",
        "bonus": 0
      }
    },
    {
      "id": -1,
      "amount": 0,
      "slot": 0,
      "bonus": {
        "effect": "NOTHING",
        "rarity": "COMMON",
        "bonus": 0
      }
    },
    {
      "id": -1,
      "amount": 0,
      "slot": 0,
      "bonus": {
        "effect": "NOTHING",
        "rarity": "COMMON",
        "bonus": 0
      }
    },
    {
      "id": -1,
      "amount": 0,
      "slot": 0,
      "bonus": {
        "effect": "NOTHING",
        "rarity": "COMMON",
        "bonus": 0
      }
    },
    {
      "id": -1,
      "amount": 0,
      "slot": 0,
      "bonus": {
        "effect": "NOTHING",
        "rarity": "COMMON",
        "bonus": 0
      }
    },
    {
      "id": -1,
      "amount": 0,
      "slot": 0,
      "bonus": {
        "effect": "NOTHING",
        "rarity": "COMMON",
        "bonus": 0
      }
    },
    {
      "id": -1,
      "amount": 0,
      "slot": 0,
      "bonus": {
        "effect": "NOTHING",
        "rarity": "COMMON",
        "bonus": 0
      }
    },
    {
      "id": -1,
      "amount": 0,
      "slot": 0,
      "bonus": {
        "effect": "NOTHING",
        "rarity": "COMMON",
        "bonus": 0
      }
    },
    {
      "id": -1,
      "amount": 0,
      "slot": 0,
      "bonus": {
        "effect": "NOTHING",
        "rarity": "COMMON",
        "bonus": 0
      }
    },
    {
      "id": -1,
      "amount": 0,
      "slot": 0,
      "bonus": {
        "effect": "NOTHING",
        "rarity": "COMMON",
        "bonus": 0
      }
    },
    {
      "id": -1,
      "amount": 0,
      "slot": 0,
      "bonus": {
        "effect": "NOTHING",
        "rarity": "COMMON",
        "bonus": 0
      }
    },
    {
      "id": -1,
      "amount": 0,
      "slot": 0,
      "bonus": {
        "effect": "NOTHING",
        "rarity": "COMMON",
        "bonus": 0
      }
    },
    {
      "id": -1,
      "amount": 0,
      "slot": 0,
      "bonus": {
        "effect": "NOTHING",
        "rarity": "COMMON",
        "bonus": 0
      }
    },
    {
      "id": -1,
      "amount": 0,
      "slot": 0,
      "bonus": {
        "effect": "NOTHING",
        "rarity": "COMMON",
        "bonus": 0
      }
    },
    {
      "id": -1,
      "amount": 0,
      "slot": 0,
      "bonus": {
        "effect": "NOTHING",
        "rarity": "COMMON",
        "bonus": 0
      }
    },
    {
      "id": -1,
      "amount": 0,
      "slot": 0,
      "bonus": {
        "effect": "NOTHING",
        "rarity": "COMMON",
        "bonus": 0
      }
    },
    {
      "id": -1,
      "amount": 0,
      "slot": 0,
      "bonus": {
        "effect": "NOTHING",
        "rarity": "COMMON",
        "bonus": 0
      }
    },
    {
      "id": -1,
      "amount": 0,
      "slot": 0,
      "bonus": {
        "effect": "NOTHING",
        "rarity": "COMMON",
        "bonus": 0
      }
    },
    {
      "id": -1,
      "amount": 0,
      "slot": 0,
      "bonus": {
        "effect": "NOTHING",
        "rarity": "COMMON",
        "bonus": 0
      }
    },
    {
      "id": -1,
      "amount": 0,
      "slot": 0,
      "bonus": {
        "effect": "NOTHING",
        "rarity": "COMMON",
        "bonus": 0
      }
    },
    {
      "id": -1,
      "amount": 0,
      "slot": 0,
      "bonus": {
        "effect": "NOTHING",
        "rarity": "COMMON",
        "bonus": 0
      }
    },
    {
      "id": -1,
      "amount": 0,
      "slot": 0,
      "bonus": {
        "effect": "NOTHING",
        "rarity": "COMMON",
        "bonus": 0
      }
    },
    {
      "id": -1,
      "amount": 0,
      "slot": 0,
      "bonus": {
        "effect": "NOTHING",
        "rarity": "COMMON",
        "bonus": 0
      }
    },
    {
      "id": -1,
      "amount": 0,
      "slot": 0,
      "bonus": {
        "effect": "NOTHING",
        "rarity": "COMMON",
        "bonus": 0
      }
    },
    {
      "id": -1,
      "amount": 0,
      "slot": 0,
      "bonus": {
        "effect": "NOTHING",
        "rarity": "COMMON",
        "bonus": 0
      }
    },
    {
      "id": -1,
      "amount": 0,
      "slot": 0,
      "bonus": {
        "effect": "NOTHING",
        "rarity": "COMMON",
        "bonus": 0
      }
    },
    {
      "id": -1,
      "amount": 0,
      "slot": 0,
      "bonus": {
        "effect": "NOTHING",
        "rarity": "COMMON",
        "bonus": 0
      }
    }
  ],
  "hcimdungequipment": [
    {
      "id": -1,
      "amount": 0,
      "slot": 0,
      "bonus": {
        "effect": "NOTHING",
        "rarity": "COMMON",
        "bonus": 0
      }
    },
    {
      "id": -1,
      "amount": 0,
      "slot": 0,
      "bonus": {
        "effect": "NOTHING",
        "rarity": "COMMON",
        "bonus": 0
      }
    },
    {
      "id": -1,
      "amount": 0,
      "slot": 0,
      "bonus": {
        "effect": "NOTHING",
        "rarity": "COMMON",
        "bonus": 0
      }
    },
    {
      "id": -1,
      "amount": 0,
      "slot": 0,
      "bonus": {
        "effect": "NOTHING",
        "rarity": "COMMON",
        "bonus": 0
      }
    },
    {
      "id": -1,
      "amount": 0,
      "slot": 0,
      "bonus": {
        "effect": "NOTHING",
        "rarity": "COMMON",
        "bonus": 0
      }
    },
    {
      "id": -1,
      "amount": 0,
      "slot": 0,
      "bonus": {
        "effect": "NOTHING",
        "rarity": "COMMON",
        "bonus": 0
      }
    },
    {
      "id": -1,
      "amount": 0,
      "slot": 0,
      "bonus": {
        "effect": "NOTHING",
        "rarity": "COMMON",
        "bonus": 0
      }
    },
    {
      "id": -1,
      "amount": 0,
      "slot": 0,
      "bonus": {
        "effect": "NOTHING",
        "rarity": "COMMON",
        "bonus": 0
      }
    },
    {
      "id": -1,
      "amount": 0,
      "slot": 0,
      "bonus": {
        "effect": "NOTHING",
        "rarity": "COMMON",
        "bonus": 0
      }
    },
    {
      "id": -1,
      "amount": 0,
      "slot": 0,
      "bonus": {
        "effect": "NOTHING",
        "rarity": "COMMON",
        "bonus": 0
      }
    },
    {
      "id": -1,
      "amount": 0,
      "slot": 0,
      "bonus": {
        "effect": "NOTHING",
        "rarity": "COMMON",
        "bonus": 0
      }
    },
    {
      "id": -1,
      "amount": 0,
      "slot": 0,
      "bonus": {
        "effect": "NOTHING",
        "rarity": "COMMON",
        "bonus": 0
      }
    },
    {
      "id": -1,
      "amount": 0,
      "slot": 0,
      "bonus": {
        "effect": "NOTHING",
        "rarity": "COMMON",
        "bonus": 0
      }
    },
    {
      "id": -1,
      "amount": 0,
      "slot": 0,
      "bonus": {
        "effect": "NOTHING",
        "rarity": "COMMON",
        "bonus": 0
      }
    },
    {
      "id": -1,
      "amount": 0,
      "slot": 0,
      "bonus": {
        "effect": "NOTHING",
        "rarity": "COMMON",
        "bonus": 0
      }
    },
    {
      "id": -1,
      "amount": 0,
      "slot": 0,
      "bonus": {
        "effect": "NOTHING",
        "rarity": "COMMON",
        "bonus": 0
      }
    },
    {
      "id": -1,
      "amount": 0,
      "slot": 0,
      "bonus": {
        "effect": "NOTHING",
        "rarity": "COMMON",
        "bonus": 0
      }
    },
    {
      "id": -1,
      "amount": 0,
      "slot": 0,
      "bonus": {
        "effect": "NOTHING",
        "rarity": "COMMON",
        "bonus": 0
      }
    },
    {
      "id": -1,
      "amount": 0,
      "slot": 0,
      "bonus": {
        "effect": "NOTHING",
        "rarity": "COMMON",
        "bonus": 0
      }
    },
    {
      "id": -1,
      "amount": 0,
      "slot": 0,
      "bonus": {
        "effect": "NOTHING",
        "rarity": "COMMON",
        "bonus": 0
      }
    },
    {
      "id": -1,
      "amount": 0,
      "slot": 0,
      "bonus": {
        "effect": "NOTHING",
        "rarity": "COMMON",
        "bonus": 0
      }
    },
    {
      "id": -1,
      "amount": 0,
      "slot": 0,
      "bonus": {
        "effect": "NOTHING",
        "rarity": "COMMON",
        "bonus": 0
      }
    },
    {
      "id": -1,
      "amount": 0,
      "slot": 0,
      "bonus": {
        "effect": "NOTHING",
        "rarity": "COMMON",
        "bonus": 0
      }
    },
    {
      "id": -1,
      "amount": 0,
      "slot": 0,
      "bonus": {
        "effect": "NOTHING",
        "rarity": "COMMON",
        "bonus": 0
      }
    },
    {
      "id": -1,
      "amount": 0,
      "slot": 0,
      "bonus": {
        "effect": "NOTHING",
        "rarity": "COMMON",
        "bonus": 0
      }
    },
    {
      "id": -1,
      "amount": 0,
      "slot": 0,
      "bonus": {
        "effect": "NOTHING",
        "rarity": "COMMON",
        "bonus": 0
      }
    },
    {
      "id": -1,
      "amount": 0,
      "slot": 0,
      "bonus": {
        "effect": "NOTHING",
        "rarity": "COMMON",
        "bonus": 0
      }
    },
    {
      "id": -1,
      "amount": 0,
      "slot": 0,
      "bonus": {
        "effect": "NOTHING",
        "rarity": "COMMON",
        "bonus": 0
      }
    }
  ],
  "bonecrusheffect": true,
  "p-tps": [
    0,
    0,
    0,
    0
  ],
  "yell-tit": "null",
  "afkstall1": 0,
  "afkstall2": 0,
  "afkstall3": 0,
  "achievements-points": 0,
  "achievements-amount": [
    [
      0,
      101,
      0,
      0,
      0,
      250,
      250,
      250,
      350,
      20,
      400,
      364,
      400,
      400,
      500,
      100,
      5000,
      45,
      0,
      0,
      0,
      0,
      0,
      0,
      0,
      0,
      0,
      0,
      0,
      0,
      0,
      0,
      0,
      0,
      0,
      0,
      0,
      0,
      0,
      0,
      0,
      0,
      0,
      0,
      0,
      0,
      0,
      0,
      0,
      0,
      0,
      0,
      0,
      0,
      0,
      0,
      0,
      0,
      0,
      0,
      0,
      0,
      0,
      0,
      0,
      0,
      0,
      0,
      0,
      0,
      0,
      0,
      0,
      0,
      0,
      0,
      0,
      0,
      0,
      0,
      0,
      0,
      0,
      0,
      0,
      0,
      0,
      0,
      0,
      0,
      0,
      0,
      0,
      0,
      0,
      0,
      0,
      0,
      0,
      0
    ],
    [
      0,
      101,
      0,
      0,
      0,
      106,
      0,
      249,
      170,
      50,
      441,
      79,
      263,
      0,
      768,
      1000,
      10000,
      0,
      0,
      0,
      0,
      0,
      0,
      0,
      0,
      0,
      0,
      0,
      0,
      0,
      0,
      0,
      0,
      0,
      0,
      0,
      0,
      0,
      0,
      0,
      0,
      0,
      0,
      0,
      0,
      0,
      0,
      0,
      0,
      0,
      0,
      0,
      0,
      0,
      0,
      0,
      0,
      0,
      0,
      0,
      0,
      0,
      0,
      0,
      0,
      0,
      0,
      0,
      0,
      0,
      0,
      0,
      0,
      0,
      0,
      0,
      0,
      0,
      0,
      0,
      0,
      0,
      0,
      0,
      0,
      0,
      0,
      0,
      0,
      0,
      0,
      0,
      0,
      0,
      0,
      0,
      0,
      0,
      0,
      0
    ],
    [
      0,
      101,
      2000,
      605,
      1256,
      563,
      454,
      173,
      812,
      111,
      462,
      798,
      759,
      675,
      127,
      0,
      10000,
      17100,
      0,
      0,
      0,
      0,
      0,
      0,
      0,
      0,
      0,
      0,
      0,
      0,
      0,
      0,
      0,
      0,
      0,
      0,
      0,
      0,
      0,
      0,
      0,
      0,
      0,
      0,
      0,
      0,
      0,
      0,
      0,
      0,
      0,
      0,
      0,
      0,
      0,
      0,
      0,
      0,
      0,
      0,
      0,
      0,
      0,
      0,
      0,
      0,
      0,
      0,
      0,
      0,
      0,
      0,
      0,
      0,
      0,
      0,
      0,
      0,
      0,
      0,
      0,
      0,
      0,
      0,
      0,
      0,
      0,
      0,
      0,
      0,
      0,
      0,
      0,
      0,
      0,
      0,
      0,
      0,
      0,
      0
    ],
    [
      0,
      0,
      0,
      0,
      0,
      0,
      0,
      0,
      0,
      0,
      0,
      0,
      0,
      0,
      0,
      0,
      0,
      0,
      0,
      0,
      0,
      0,
      0,
      0,
      0,
      0,
      0,
      0,
      0,
      0,
      0,
      0,
      0,
      0,
      0,
      0,
      0,
      0,
      0,
      0,
      0,
      0,
      0,
      0,
      0,
      0,
      0,
      0,
      0,
      0,
      0,
      0,
      0,
      0,
      0,
      0,
      0,
      0,
      0,
      0,
      0,
      0,
      0,
      0,
      0,
      0,
      0,
      0,
      0,
      0,
      0,
      0,
      0,
      0,
      0,
      0,
      0,
      0,
      0,
      0,
      0,
      0,
      0,
      0,
      0,
      0,
      0,
      0,
      0,
      0,
      0,
      0,
      0,
      0,
      0,
      0,
      0,
      0,
      0,
      0
    ]
  ],
  "achievements-completed": [
    [
      false,
      true,
      false,
      false,
      false,
      true,
      true,
      true,
      true,
      true,
      true,
      false,
      true,
      true,
      true,
      true,
      true,
      true,
      false,
      false,
      false,
      false,
      false,
      false,
      false,
      false,
      false,
      false,
      false,
      false,
      false,
      false,
      false,
      false,
      false,
      false,
      false,
      false,
      false,
      false,
      false,
      false,
      false,
      false,
      false,
      false,
      false,
      false,
      false,
      false,
      false,
      false,
      false,
      false,
      false,
      false,
      false,
      false,
      false,
      false,
      false,
      false,
      false,
      false,
      false,
      false,
      false,
      false,
      false,
      false,
      false,
      false,
      false,
      false,
      false,
      false,
      false,
      false,
      false,
      false,
      false,
      false,
      false,
      false,
      false,
      false,
      false,
      false,
      false,
      false,
      false,
      false,
      false,
      false,
      false,
      false,
      false,
      false,
      false,
      false
    ],
    [
      false,
      true,
      false,
      false,
      false,
      false,
      false,
      false,
      false,
      true,
      false,
      false,
      false,
      false,
      false,
      true,
      true,
      false,
      false,
      false,
      false,
      false,
      false,
      false,
      false,
      false,
      false,
      false,
      false,
      false,
      false,
      false,
      false,
      false,
      false,
      false,
      false,
      false,
      false,
      false,
      false,
      false,
      false,
      false,
      false,
      false,
      false,
      false,
      false,
      false,
      false,
      false,
      false,
      false,
      false,
      false,
      false,
      false,
      false,
      false,
      false,
      false,
      false,
      false,
      false,
      false,
      false,
      false,
      false,
      false,
      false,
      false,
      false,
      false,
      false,
      false,
      false,
      false,
      false,
      false,
      false,
      false,
      false,
      false,
      false,
      false,
      false,
      false,
      false,
      false,
      false,
      false,
      false,
      false,
      false,
      false,
      false,
      false,
      false,
      false
    ],
    [
      false,
      true,
      true,
      false,
      false,
      false,
      false,
      false,
      false,
      false,
      false,
      false,
      false,
      false,
      false,
      false,
      true,
      false,
      false,
      false,
      false,
      false,
      false,
      false,
      false,
      false,
      false,
      false,
      false,
      false,
      false,
      false,
      false,
      false,
      false,
      false,
      false,
      false,
      false,
      false,
      false,
      false,
      false,
      false,
      false,
      false,
      false,
      false,
      false,
      false,
      false,
      false,
      false,
      false,
      false,
      false,
      false,
      false,
      false,
      false,
      false,
      false,
      false,
      false,
      false,
      false,
      false,
      false,
      false,
      false,
      false,
      false,
      false,
      false,
      false,
      false,
      false,
      false,
      false,
      false,
      false,
      false,
      false,
      false,
      false,
      false,
      false,
      false,
      false,
      false,
      false,
      false,
      false,
      false,
      false,
      false,
      false,
      false,
      false,
      false
    ],
    [
      false,
      false,
      false,
      false,
      false,
      false,
      false,
      false,
      false,
      false,
      false,
      false,
      false,
      false,
      false,
      false,
      false,
      false,
      false,
      false,
      false,
      false,
      false,
      false,
      false,
      false,
      false,
      false,
      false,
      false,
      false,
      false,
      false,
      false,
      false,
      false,
      false,
      false,
      false,
      false,
      false,
      false,
      false,
      false,
      false,
      false,
      false,
      false,
      false,
      false,
      false,
      false,
      false,
      false,
      false,
      false,
      false,
      false,
      false,
      false,
      false,
      false,
      false,
      false,
      false,
      false,
      false,
      false,
      false,
      false,
      false,
      false,
      false,
      false,
      false,
      false,
      false,
      false,
      false,
      false,
      false,
      false,
      false,
      false,
      false,
      false,
      false,
      false,
      false,
      false,
      false,
      false,
      false,
      false,
      false,
      false,
      false,
      false,
      false,
      false
    ]
  ],
  "achievements-daily": 323,
  "progression-zones": [
    10,
    21,
    30,
    42,
    75
  ],
  "zones-complete": [
    true,
    true,
    true,
    true,
    true
  ],
  "gamble-banned": false,
  "lucifers-unlocked": false,
  "dark-supremes-unlocked": false,
  "currency-pouch": {
    "upgradeTokens": 0,
    "pvmTickets": 0,
    "afkTickets": 0,
    "slayerTickets": 0,
    "voteScrolls": 0,
    "petFragments": 0,
    "instanceTokens": 0,
    "goldCharms": 0,
    "greenCharms": 0,
    "crimsonCharms": 0,
    "blueCharms": 0
  },
  "lastTGloveIndex": -1,
  "group-ironman-locked": false,
  "lastInstanceNpc": 9017,
  "daily-task": {},
  "collectionlog-rewards": {
    "9024": {
      "canClaim": false,
      "hasClaimed": false
    },
    "9920": {
      "canClaim": false,
      "hasClaimed": false
    },
    "9025": {
      "canClaim": false,
      "hasClaimed": false
    },
    "3010": {
      "canClaim": false,
      "hasClaimed": false
    },
    "8002": {
      "canClaim": false,
      "hasClaimed": false
    },
    "9026": {
      "canClaim": false,
      "hasClaimed": false
    },
    "9922": {
      "canClaim": false,
      "hasClaimed": false
    },
    "8003": {
      "canClaim": false,
      "hasClaimed": false
    },
    "9027": {
      "canClaim": false,
      "hasClaimed": false
    },
    "3013": {
      "canClaim": false,
      "hasClaimed": false
    },
    "3014": {
      "canClaim": false,
      "hasClaimed": false
    },
    "3016": {
      "canClaim": false,
      "hasClaimed": false
    },
    "8008": {
      "canClaim": false,
      "hasClaimed": false
    },
    "8010": {
      "canClaim": false,
      "hasClaimed": false
    },
    "202": {
      "canClaim": false,
      "hasClaimed": false
    },
    "8013": {
      "canClaim": false,
      "hasClaimed": false
    },
    "9806": {
      "canClaim": false,
      "hasClaimed": false
    },
    "8014": {
      "canClaim": true,
      "hasClaimed": true
    },
    "9807": {
      "canClaim": false,
      "hasClaimed": false
    },
    "1746": {
      "canClaim": false,
      "hasClaimed": false
    },
    "9815": {
      "canClaim": false,
      "hasClaimed": false
    },
    "9816": {
      "canClaim": false,
      "hasClaimed": false
    },
    "9817": {
      "canClaim": false,
      "hasClaimed": false
    },
    "6692": {
      "canClaim": true,
      "hasClaimed": true
    },
    "2342": {
      "canClaim": false,
      "hasClaimed": false
    },
    "811": {
      "canClaim": false,
      "hasClaimed": false
    },
    "9835": {
      "canClaim": false,
      "hasClaimed": false
    },
    "9837": {
      "canClaim": false,
      "hasClaimed": false
    },
    "9838": {
      "canClaim": false,
      "hasClaimed": false
    },
    "9903": {
      "canClaim": false,
      "hasClaimed": false
    },
    "9839": {
      "canClaim": false,
      "hasClaimed": false
    },
    "9904": {
      "canClaim": false,
      "hasClaimed": false
    },
    "9906": {
      "canClaim": false,
      "hasClaimed": false
    },
    "9907": {
      "canClaim": false,
      "hasClaimed": false
    },
    "9908": {
      "canClaim": false,
      "hasClaimed": false
    },
    "9845": {
      "canClaim": false,
      "hasClaimed": false
    },
    "9910": {
      "canClaim": false,
      "hasClaimed": false
    },
    "3831": {
      "canClaim": true,
      "hasClaimed": true
    },
    "9911": {
      "canClaim": false,
      "hasClaimed": false
    },
    "9017": {
      "canClaim": false,
      "hasClaimed": false
    },
    "9914": {
      "canClaim": false,
      "hasClaimed": false
    },
    "9915": {
      "canClaim": false,
      "hasClaimed": false
    },
    "9916": {
      "canClaim": false,
      "hasClaimed": false
    },
    "9918": {
      "canClaim": false,
      "hasClaimed": false
    }
  },
  "daily-skips": 3,
  "dailies-done": 3,
  "daily-task-info": "Your daily task is: @red@Kill 2 global bosses. @bla@Progress: @red@2/2@bla@.",
  "level-notifications": true,
  "dailies-received-times": [
    1681916414857,
    1681941119559,
    1681952209293
  ],
  "favorite-teleports": [],
  "obtained-pets": [
    "SANCTUM_GOLEM_PET",
    "CALAMITY_PET",
    "LILINRYSS_PET"
  ],
  "battlepass-xp": 0,
  "battlepass-premium": false,
  "mini-me-equipment": [
    null,
    null,
    null,
    null,
    null,
    null,
    null,
    null,
    null,
    null,
    null,
    null,
    null,
    null
  ],
  "drystreak": {
    "9024": 157,
    "9920": 74,
    "9025": 4,
    "3010": 232,
    "8002": 173,
    "9026": 114,
    "9922": 64,
    "8003": 5,
    "9027": 13,
    "3013": 798,
    "3014": 173,
    "3016": 127,
    "8008": 106,
    "8010": 675,
    "202": 33,
    "8013": 0,
    "9806": 1256,
    "8014": 6,
    "9807": 8,
    "1746": 812,
    "9815": 76,
    "9816": 563,
    "9817": 70,
    "6692": 1,
    "2342": 170,
    "811": 27,
    "9835": 30,
    "9837": 10,
    "9838": 4,
    "9903": 454,
    "9839": 605,
    "9904": 0,
    "9906": 0,
    "9907": 0,
    "9908": 0,
    "9845": 0,
    "9910": 3,
    "3831": 67,
    "9911": 20,
    "9017": 102,
    "9914": 168,
    "9915": 37,
    "9916": 79,
    "9918": 23
  },
  "boost": 0,
  "slot-level": 0
}