{
  "shop-history": [
    {
      "id": 23020,
      "amount": 5,
      "buyer": "Slayer",
      "price": 25000,
      "effect": "NOTHING",
      "bonus": 0
    },
    {
      "id": 10946,
      "amount": 10,
      "buyer": "Zshana",
      "price": 48500,
      "effect": "NOTHING",
      "bonus": 0
    },
    {
      "id": 10946,
      "amount": 1,
      "buyer": "Zshana",
      "price": 48500,
      "effect": "NOTHING",
      "bonus": 0
    },
    {
      "id": 10946,
      "amount": 10,
      "buyer": "Onlyfans",
      "price": 50000,
      "effect": "NOTHING",
      "bonus": 0
    },
    {
      "id": 10946,
      "amount": 5,
      "buyer": "Onlyfans",
      "price": 50000,
      "effect": "NOTHING",
      "bonus": 0
    },
    {
      "id": 23057,
      "amount": 1,
      "buyer": "Onlyfans",
      "price": 500000,
      "effect": "NOTHING",
      "bonus": 0
    },
    {
      "id": 10946,
      "amount": 10,
      "buyer": "Suh",
      "price": 65000,
      "effect": "NOTHING",
      "bonus": 0
    },
    {
      "id": 12610,
      "amount": 1,
      "buyer": "Neff",
      "price": 50000,
      "effect": "DROP_RATE_LOW",
      "bonus": 20
    },
    {
      "id": 22125,
      "amount": 1,
      "buyer": "Lewa",
      "price": 28000,
      "effect": "NOTHING",
      "bonus": 0
    },
    {
      "id": 10946,
      "amount": 10,
      "buyer": "Onlyfans",
      "price": 55000,
      "effect": "NOTHING",
      "bonus": 0
    },
    {
      "id": 10946,
      "amount": 10,
      "buyer": "Onlyfans",
      "price": 55000,
      "effect": "NOTHING",
      "bonus": 0
    },
    {
      "id": 23057,
      "amount": 1,
      "buyer": "Onlyfans",
      "price": 550000,
      "effect": "NOTHING",
      "bonus": 0
    },
    {
      "id": 10946,
      "amount": 10,
      "buyer": "Like My Peep",
      "price": 55000,
      "effect": "NOTHING",
      "bonus": 0
    },
    {
      "id": 10946,
      "amount": 7,
      "buyer": "Like My Peep",
      "price": 55000,
      "effect": "NOTHING",
      "bonus": 0
    },
    {
      "id": 13964,
      "amount": 1,
      "buyer": "Ctg804",
      "price": 500000,
      "effect": "MAGIC_DAMAGE",
      "bonus": 1
    },
    {
      "id": 23165,
      "amount": 1,
      "buyer": "Resi",
      "price": 1000000,
      "effect": "NOTHING",
      "bonus": 0
    },
    {
      "id": 23075,
      "amount": 1,
      "buyer": "Slussy",
      "price": 525000,
      "effect": "NOTHING",
      "bonus": 0
    },
    {
      "id": 22149,
      "amount": 1,
      "buyer": "Igotplugz",
      "price": 350000,
      "effect": "NOTHING",
      "bonus": 0
    },
    {
      "id": 23057,
      "amount": 2,
      "buyer": "Gizeh",
      "price": 600000,
      "effect": "NOTHING",
      "bonus": 0
    },
    {
      "id": 10946,
      "amount": 3,
      "buyer": "Matt0804",
      "price": 60000,
      "effect": "NOTHING",
      "bonus": 0
    },
    {
      "id": 10946,
      "amount": 42,
      "buyer": "Matt0804",
      "price": 60000,
      "effect": "NOTHING",
      "bonus": 0
    },
    {
      "id": 23057,
      "amount": 1,
      "buyer": "Onlyfans",
      "price": 600000,
      "effect": "NOTHING",
      "bonus": 0
    },
    {
      "id": 23058,
      "amount": 3,
      "buyer": "Onlyfans",
      "price": 1500000,
      "effect": "NOTHING",
      "bonus": 0
    },
    {
      "id": 19491,
      "amount": 1,
      "buyer": "Dustspray",
      "price": 400000,
      "effect": "NOTHING",
      "bonus": 0
    },
    {
      "id": 10946,
      "amount": 6,
      "buyer": "A Fatality",
      "price": 60000,
      "effect": "NOTHING",
      "bonus": 0
    },
    {
      "id": 8788,
      "amount": 3,
      "buyer": "Inherited",
      "price": 120000,
      "effect": "NOTHING",
      "bonus": 0
    },
    {
      "id": 10946,
      "amount": 1,
      "buyer": "Redx12",
      "price": 60000,
      "effect": "NOTHING",
      "bonus": 0
    },
    {
      "id": 8788,
      "amount": 10,
      "buyer": "Jroc",
      "price": 120000,
      "effect": "NOTHING",
      "bonus": 0
    },
    {
      "id": 8788,
      "amount": 9,
      "buyer": "Jroc",
      "price": 120000,
      "effect": "NOTHING",
      "bonus": 0
    },
    {
      "id": 22135,
      "amount": 1,
      "buyer": "Gizeh",
      "price": 23000000,
      "effect": "AOE_EFFECT",
      "bonus": 1
    }
  ]
}