{
  "shop-history": [
    {
      "id": 11001,
      "amount": 1,
      "buyer": "Boterkoek",
      "price": 75000,
      "effect": "ALL_DAMAGE_HIGH",
      "bonus": 3
    },
    {
      "id": 23063,
      "amount": 1,
      "buyer": "Isyutaru",
      "price": 200000,
      "effect": "TRIPLE_KILLS",
      "bonus": 2
    },
    {
      "id": 5012,
      "amount": 1,
      "buyer": "Onlyfans",
      "price": 280000,
      "effect": "NOTHING",
      "bonus": 0
    },
    {
      "id": 21022,
      "amount": 1,
      "buyer": "Inherited",
      "price": 80000,
      "effect": "MAGIC_DAMAGE",
      "bonus": 1
    },
    {
      "id": 8820,
      "amount": 1,
      "buyer": "Kingrock",
      "price": 10000,
      "effect": "DOUBLE_DROP",
      "bonus": 11
    },
    {
      "id": 17606,
      "amount": 1,
      "buyer": "Inherited",
      "price": 80000,
      "effect": "NOTHING",
      "bonus": 0
    },
    {
      "id": 23066,
      "amount": 1,
      "buyer": "Divine",
      "price": 150000,
      "effect": "ALL_DAMAGE_HIGH",
      "bonus": 3
    },
    {
      "id": 12612,
      "amount": 1,
      "buyer": "Johnnyapple",
      "price": 200000,
      "effect": "ALL_DAMAGE_MEDIUM",
      "bonus": 2
    },
    {
      "id": 1485,
      "amount": 1,
      "buyer": "Damlegend",
      "price": 30000,
      "effect": "DROP_RATE_LOW",
      "bonus": 17
    },
    {
      "id": 12614,
      "amount": 1,
      "buyer": "Scary Terry",
      "price": 80000,
      "effect": "DROP_RATE_LOW",
      "bonus": 5
    },
    {
      "id": 8819,
      "amount": 1,
      "buyer": "Supernum",
      "price": 50000,
      "effect": "DROP_RATE_LOW",
      "bonus": 16
    },
    {
      "id": 1857,
      "amount": 1,
      "buyer": "Onlyfans",
      "price": 250000,
      "effect": "NOTHING",
      "bonus": 0
    },
    {
      "id": 4685,
      "amount": 1,
      "buyer": "Weed",
      "price": 100000,
      "effect": "RANGE_DAMAGE",
      "bonus": 1
    },
    {
      "id": 22136,
      "amount": 1,
      "buyer": "Kingrock",
      "price": 300000,
      "effect": "MAGIC_DAMAGE",
      "bonus": 1
    },
    {
      "id": 16194,
      "amount": 1,
      "buyer": "Light",
      "price": 100000,
      "effect": "DOUBLE_DROP",
      "bonus": 8
    },
    {
      "id": 16194,
      "amount": 1,
      "buyer": "Cameron",
      "price": 100000,
      "effect": "ALL_DAMAGE_LOW",
      "bonus": 1
    },
    {
      "id": 12614,
      "amount": 1,
      "buyer": "Cameron",
      "price": 50000,
      "effect": "NOTHING",
      "bonus": 0
    },
    {
      "id": 16194,
      "amount": 1,
      "buyer": "Kebab",
      "price": 100000,
      "effect": "ALL_DAMAGE_LOW",
      "bonus": 1
    },
    {
      "id": 11195,
      "amount": 1,
      "buyer": "Madara",
      "price": 80000,
      "effect": "NOTHING",
      "bonus": 0
    },
    {
      "id": 23061,
      "amount": 1,
      "buyer": "Damlegend",
      "price": 100000,
      "effect": "RANGE_DAMAGE",
      "bonus": 1
    },
    {
      "id": 17686,
      "amount": 1,
      "buyer": "Moralizer",
      "price": 30000,
      "effect": "NOTHING",
      "bonus": 0
    },
    {
      "id": 15935,
      "amount": 1,
      "buyer": "Aspas",
      "price": 80000,
      "effect": "DOUBLE_DROP",
      "bonus": 5
    },
    {
      "id": 15924,
      "amount": 1,
      "buyer": "Aspas",
      "price": 80000,
      "effect": "DROP_RATE_LOW",
      "bonus": 18
    },
    {
      "id": 12612,
      "amount": 1,
      "buyer": "Kingrock",
      "price": 150000,
      "effect": "ALL_DAMAGE_MEDIUM",
      "bonus": 2
    },
    {
      "id": 8814,
      "amount": 1,
      "buyer": "Jroc",
      "price": 100000,
      "effect": "RANGE_DAMAGE",
      "bonus": 1
    },
    {
      "id": 22137,
      "amount": 1,
      "buyer": "Jroc",
      "price": 200000,
      "effect": "NOTHING",
      "bonus": 0
    },
    {
      "id": 19918,
      "amount": 1,
      "buyer": "Forest",
      "price": 500000,
      "effect": "DOUBLE_KILLS",
      "bonus": 2
    },
    {
      "id": 19918,
      "amount": 1,
      "buyer": "Cameron",
      "price": 500000,
      "effect": "DOUBLE_KILLS",
      "bonus": 2
    },
    {
      "id": 11001,
      "amount": 1,
      "buyer": "Xtra25",
      "price": 20000,
      "effect": "DOUBLE_DROP",
      "bonus": 10
    },
    {
      "id": 23068,
      "amount": 1,
      "buyer": "L I T S",
      "price": 100000,
      "effect": "DOUBLE_KILLS",
      "bonus": 2
    },
    {
      "id": 17694,
      "amount": 1,
      "buyer": "Kingrock",
      "price": 700000,
      "effect": "DROP_RATE_HIGH",
      "bonus": 80
    },
    {
      "id": 22103,
      "amount": 1,
      "buyer": "Ctg804",
      "price": 500000,
      "effect": "NOTHING",
      "bonus": 0
    },
    {
      "id": 22154,
      "amount": 1,
      "buyer": "Gekyume",
      "price": 200000,
      "effect": "NOTHING",
      "bonus": 0
    },
    {
      "id": 23075,
      "amount": 1,
      "buyer": "Star",
      "price": 500000,
      "effect": "DROP_RATE_HIGH",
      "bonus": 38
    },
    {
      "id": 22154,
      "amount": 1,
      "buyer": "Star",
      "price": 200000,
      "effect": "NOTHING",
      "bonus": 0
    },
    {
      "id": 22153,
      "amount": 1,
      "buyer": "Gekyume",
      "price": 800000,
      "effect": "NOTHING",
      "bonus": 0
    },
    {
      "id": 22155,
      "amount": 2,
      "buyer": "Zshana",
      "price": 900000,
      "effect": "NOTHING",
      "bonus": 0
    },
    {
      "id": 20095,
      "amount": 1,
      "buyer": "Vaflius",
      "price": 250000,
      "effect": "NOTHING",
      "bonus": 0
    },
    {
      "id": 17606,
      "amount": 1,
      "buyer": "Vaflius",
      "price": 100000,
      "effect": "NOTHING",
      "bonus": 0
    },
    {
      "id": 11195,
      "amount": 1,
      "buyer": "Hc Pvm",
      "price": 100000,
      "effect": "NOTHING",
      "bonus": 0
    },
    {
      "id": 23057,
      "amount": 1,
      "buyer": "Zaryte",
      "price": 300000,
      "effect": "NOTHING",
      "bonus": 0
    },
    {
      "id": 22137,
      "amount": 1,
      "buyer": "Rotter",
      "price": 400000,
      "effect": "NOTHING",
      "bonus": 0
    },
    {
      "id": 19886,
      "amount": 1,
      "buyer": "Inherited",
      "price": 150000,
      "effect": "DOUBLE_CASH",
      "bonus": 1
    },
    {
      "id": 19886,
      "amount": 1,
      "buyer": "Mondo",
      "price": 150000,
      "effect": "DOUBLE_CASH",
      "bonus": 1
    },
    {
      "id": 22153,
      "amount": 1,
      "buyer": "Ctg804",
      "price": 800000,
      "effect": "NOTHING",
      "bonus": 0
    },
    {
      "id": 11195,
      "amount": 1,
      "buyer": "Mana",
      "price": 150000,
      "effect": "NOTHING",
      "bonus": 0
    },
    {
      "id": 23049,
      "amount": 1,
      "buyer": "Duke",
      "price": 200000,
      "effect": "NOTHING",
      "bonus": 0
    },
    {
      "id": 23049,
      "amount": 1,
      "buyer": "Scary Terry",
      "price": 200000,
      "effect": "NOTHING",
      "bonus": 0
    },
    {
      "id": 22167,
      "amount": 1,
      "buyer": "Mini",
      "price": 1800000,
      "effect": "NOTHING",
      "bonus": 0
    },
    {
      "id": 22122,
      "amount": 1,
      "buyer": "Matt0804",
      "price": 200000,
      "effect": "ALL_DAMAGE_LOW",
      "bonus": 1
    },
    {
      "id": 22153,
      "amount": 1,
      "buyer": "Hibashi",
      "price": 700000,
      "effect": "NOTHING",
      "bonus": 0
    },
    {
      "id": 19495,
      "amount": 1,
      "buyer": "Hibashi",
      "price": 700000,
      "effect": "NOTHING",
      "bonus": 0
    },
    {
      "id": 21039,
      "amount": 1,
      "buyer": "Ashwsonov",
      "price": 15000,
      "effect": "NOTHING",
      "bonus": 0
    },
    {
      "id": 20586,
      "amount": 1,
      "buyer": "Hc Pvm",
      "price": 900000,
      "effect": "NOTHING",
      "bonus": 0
    },
    {
      "id": 8411,
      "amount": 1,
      "buyer": "A Fatality",
      "price": 13000000,
      "effect": "NOTHING",
      "bonus": 0
    },
    {
      "id": 14313,
      "amount": 1,
      "buyer": "666 Coins",
      "price": 1000000,
      "effect": "NOTHING",
      "bonus": 0
    },
    {
      "id": 8412,
      "amount": 1,
      "buyer": "Ctg804",
      "price": 11000000,
      "effect": "DROP_RATE_LOW",
      "bonus": 19
    },
    {
      "id": 8814,
      "amount": 1,
      "buyer": "Bobross",
      "price": 150000,
      "effect": "NOTHING",
      "bonus": 0
    },
    {
      "id": 23092,
      "amount": 1,
      "buyer": "Ainokea",
      "price": 15000,
      "effect": "ALL_DAMAGE_LOW",
      "bonus": 1
    },
    {
      "id": 14313,
      "amount": 1,
      "buyer": "Dark",
      "price": 1000000,
      "effect": "NOTHING",
      "bonus": 0
    },
    {
      "id": 23094,
      "amount": 1,
      "buyer": "Bulba",
      "price": 15000,
      "effect": "DOUBLE_DROP",
      "bonus": 18
    },
    {
      "id": 21029,
      "amount": 1,
      "buyer": "Winalldays",
      "price": 15000,
      "effect": "NOTHING",
      "bonus": 0
    },
    {
      "id": 23049,
      "amount": 1,
      "buyer": "Gekyume",
      "price": 150000,
      "effect": "RANGE_DAMAGE",
      "bonus": 1
    },
    {
      "id": 23049,
      "amount": 1,
      "buyer": "Boms",
      "price": 50000,
      "effect": "NOTHING",
      "bonus": 0
    },
    {
      "id": 23049,
      "amount": 1,
      "buyer": "Boms",
      "price": 50000,
      "effect": "NOTHING",
      "bonus": 0
    },
    {
      "id": 23049,
      "amount": 1,
      "buyer": "Gekyume",
      "price": 150000,
      "effect": "RANGE_DAMAGE",
      "bonus": 1
    },
    {
      "id": 13640,
      "amount": 1,
      "buyer": "Pvmer95",
      "price": 200000,
      "effect": "NOTHING",
      "bonus": 0
    },
    {
      "id": 13640,
      "amount": 1,
      "buyer": "Weed",
      "price": 200000,
      "effect": "NOTHING",
      "bonus": 0
    },
    {
      "id": 15645,
      "amount": 1,
      "buyer": "Blind Shit",
      "price": 550000,
      "effect": "TRIPLE_KILLS",
      "bonus": 2
    },
    {
      "id": 13640,
      "amount": 1,
      "buyer": "Laniakea",
      "price": 400000,
      "effect": "MAGIC_DAMAGE",
      "bonus": 1
    },
    {
      "id": 11764,
      "amount": 1,
      "buyer": "Laniakea",
      "price": 4000000,
      "effect": "NOTHING",
      "bonus": 0
    },
    {
      "id": 15645,
      "amount": 1,
      "buyer": "Swigglecake",
      "price": 550000,
      "effect": "TRIPLE_KILLS",
      "bonus": 2
    },
    {
      "id": 11765,
      "amount": 1,
      "buyer": "Loonasee",
      "price": 4000000,
      "effect": "NOTHING",
      "bonus": 0
    },
    {
      "id": 13640,
      "amount": 1,
      "buyer": "Loonasee",
      "price": 400000,
      "effect": "MAGIC_DAMAGE",
      "bonus": 1
    },
    {
      "id": 13640,
      "amount": 1,
      "buyer": "Princespeach",
      "price": 500000,
      "effect": "DOUBLE_DROP",
      "bonus": 14
    },
    {
      "id": 22154,
      "amount": 1,
      "buyer": "Alakazam",
      "price": 500000,
      "effect": "MAGIC_DAMAGE",
      "bonus": 1
    },
    {
      "id": 13640,
      "amount": 1,
      "buyer": "Odin",
      "price": 300000,
      "effect": "NOTHING",
      "bonus": 0
    },
    {
      "id": 13640,
      "amount": 1,
      "buyer": "Roy",
      "price": 300000,
      "effect": "NOTHING",
      "bonus": 0
    },
    {
      "id": 22154,
      "amount": 1,
      "buyer": "Time",
      "price": 500000,
      "effect": "MAGIC_DAMAGE",
      "bonus": 1
    },
    {
      "id": 14052,
      "amount": 1,
      "buyer": "Odin",
      "price": 50000,
      "effect": "ALL_DAMAGE_LOW",
      "bonus": 1
    },
    {
      "id": 15008,
      "amount": 1,
      "buyer": "Gekyume",
      "price": 1500000,
      "effect": "TRIPLE_KILLS",
      "bonus": 1
    },
    {
      "id": 15200,
      "amount": 1,
      "buyer": "Time",
      "price": 1000000,
      "effect": "ALL_DAMAGE_LOW",
      "bonus": 1
    },
    {
      "id": 15008,
      "amount": 1,
      "buyer": "Loonasee",
      "price": 1000000,
      "effect": "DOUBLE_DROP",
      "bonus": 8
    },
    {
      "id": 15008,
      "amount": 1,
      "buyer": "Ruvk",
      "price": 1500000,
      "effect": "TRIPLE_KILLS",
      "bonus": 1
    },
    {
      "id": 15200,
      "amount": 1,
      "buyer": "Ruvk",
      "price": 1000000,
      "effect": "ALL_DAMAGE_LOW",
      "bonus": 1
    },
    {
      "id": 15201,
      "amount": 1,
      "buyer": "Ruvk",
      "price": 1000000,
      "effect": "NOTHING",
      "bonus": 0
    },
    {
      "id": 15008,
      "amount": 1,
      "buyer": "Kandonas",
      "price": 1000000,
      "effect": "DOUBLE_DROP",
      "bonus": 8
    },
    {
      "id": 13640,
      "amount": 1,
      "buyer": "Tgaming",
      "price": 500000,
      "effect": "DOUBLE_DROP",
      "bonus": 14
    },
    {
      "id": 15201,
      "amount": 1,
      "buyer": "Matt0804",
      "price": 1000000,
      "effect": "NOTHING",
      "bonus": 0
    },
    {
      "id": 21029,
      "amount": 1,
      "buyer": "Bonk",
      "price": 15000,
      "effect": "NOTHING",
      "bonus": 0
    },
    {
      "id": 20590,
      "amount": 1,
      "buyer": "Time",
      "price": 3000000,
      "effect": "NOTHING",
      "bonus": 0
    },
    {
      "id": 20590,
      "amount": 1,
      "buyer": "Sad",
      "price": 3000000,
      "effect": "NOTHING",
      "bonus": 0
    },
    {
      "id": 3107,
      "amount": 1,
      "buyer": "Bonk",
      "price": 300000,
      "effect": "NOTHING",
      "bonus": 0
    },
    {
      "id": 23167,
      "amount": 1,
      "buyer": "Boms",
      "price": 700000,
      "effect": "NOTHING",
      "bonus": 0
    },
    {
      "id": 14325,
      "amount": 1,
      "buyer": "Malevolent",
      "price": 1000000,
      "effect": "TRIPLE_KILLS",
      "bonus": 1
    },
    {
      "id": 8815,
      "amount": 1,
      "buyer": "Railtech",
      "price": 200000,
      "effect": "ALL_DAMAGE_LOW",
      "bonus": 1
    },
    {
      "id": 20590,
      "amount": 1,
      "buyer": "Clav",
      "price": 3000000,
      "effect": "NOTHING",
      "bonus": 0
    },
    {
      "id": 20604,
      "amount": 1,
      "buyer": "Pjk",
      "price": 6000000,
      "effect": "NOTHING",
      "bonus": 0
    },
    {
      "id": 22134,
      "amount": 1,
      "buyer": "Pjk",
      "price": 4000000,
      "effect": "DROP_RATE_LOW",
      "bonus": 15
    },
    {
      "id": 3107,
      "amount": 1,
      "buyer": "N00bdaxur",
      "price": 300000,
      "effect": "NOTHING",
      "bonus": 0
    },
    {
      "id": 14440,
      "amount": 2,
      "buyer": "Entropy",
      "price": 3000000,
      "effect": "NOTHING",
      "bonus": 0
    },
    {
      "id": 19888,
      "amount": 1,
      "buyer": "Xtc",
      "price": 12000000,
      "effect": "DROP_RATE_HIGH",
      "bonus": 72
    }
  ]
}