{
  "shop-history": [
    {
      "id": 10946,
      "amount": 2,
      "buyer": "A Fatality",
      "price": 35000,
      "effect": "NOTHING",
      "bonus": 0
    },
    {
      "id": 3086,
      "amount": 1,
      "buyer": "Coke",
      "price": 100000,
      "effect": "NOTHING",
      "bonus": 0
    },
    {
      "id": 3090,
      "amount": 1,
      "buyer": "Kingrock",
      "price": 100000,
      "effect": "NOTHING",
      "bonus": 0
    },
    {
      "id": 15359,
      "amount": 1,
      "buyer": "Kingrock",
      "price": 50000,
      "effect": "NOTHING",
      "bonus": 0
    },
    {
      "id": 15358,
      "amount": 2,
      "buyer": "Gekyume",
      "price": 100000,
      "effect": "NOTHING",
      "bonus": 0
    },
    {
      "id": 1033,
      "amount": 1,
      "buyer": "Coke",
      "price": 100000,
      "effect": "NOTHING",
      "bonus": 0
    },
    {
      "id": 23020,
      "amount": 5,
      "buyer": "Jroc",
      "price": 30000,
      "effect": "NOTHING",
      "bonus": 0
    },
    {
      "id": 23020,
      "amount": 2,
      "buyer": "Gizeh",
      "price": 25000,
      "effect": "NOTHING",
      "bonus": 0
    },
    {
      "id": 23020,
      "amount": 1,
      "buyer": "Gekyume",
      "price": 25000,
      "effect": "NOTHING",
      "bonus": 0
    },
    {
      "id": 10946,
      "amount": 2,
      "buyer": "Cheech",
      "price": 40000,
      "effect": "NOTHING",
      "bonus": 0
    },
    {
      "id": 10946,
      "amount": 1,
      "buyer": "Zaryte",
      "price": 45000,
      "effect": "NOTHING",
      "bonus": 0
    },
    {
      "id": 23020,
      "amount": 2,
      "buyer": "Jordu",
      "price": 25000,
      "effect": "NOTHING",
      "bonus": 0
    },
    {
      "id": 23020,
      "amount": 1,
      "buyer": "Ruthie",
      "price": 25000,
      "effect": "NOTHING",
      "bonus": 0
    },
    {
      "id": 10946,
      "amount": 5,
      "buyer": "Ruthie",
      "price": 45000,
      "effect": "NOTHING",
      "bonus": 0
    },
    {
      "id": 10946,
      "amount": 5,
      "buyer": "Zaryte",
      "price": 45000,
      "effect": "NOTHING",
      "bonus": 0
    },
    {
      "id": 10946,
      "amount": 3,
      "buyer": "Gizeh",
      "price": 45000,
      "effect": "NOTHING",
      "bonus": 0
    },
    {
      "id": 5023,
      "amount": 13,
      "buyer": "Ruthie",
      "price": 200,
      "effect": "NOTHING",
      "bonus": 0
    },
    {
      "id": 5023,
      "amount": 947,
      "buyer": "Ruthie",
      "price": 200,
      "effect": "NOTHING",
      "bonus": 0
    },
    {
      "id": 10946,
      "amount": 1,
      "buyer": "Oblivion",
      "price": 45000,
      "effect": "NOTHING",
      "bonus": 0
    },
    {
      "id": 15359,
      "amount": 1,
      "buyer": "Onlyfans",
      "price": 100000,
      "effect": "NOTHING",
      "bonus": 0
    },
    {
      "id": 10946,
      "amount": 2,
      "buyer": "Divine",
      "price": 50000,
      "effect": "NOTHING",
      "bonus": 0
    },
    {
      "id": 10946,
      "amount": 1,
      "buyer": "Redx12",
      "price": 80000,
      "effect": "NOTHING",
      "bonus": 0
    },
    {
      "id": 10946,
      "amount": 1,
      "buyer": "Redx12",
      "price": 80000,
      "effect": "NOTHING",
      "bonus": 0
    },
    {
      "id": 23020,
      "amount": 3,
      "buyer": "Rayquaza",
      "price": 55000,
      "effect": "NOTHING",
      "bonus": 0
    },
    {
      "id": 23020,
      "amount": 3,
      "buyer": "Onlyfans",
      "price": 70000,
      "effect": "NOTHING",
      "bonus": 0
    },
    {
      "id": 20552,
      "amount": 1,
      "buyer": "Magnet",
      "price": 400000,
      "effect": "NOTHING",
      "bonus": 0
    },
    {
      "id": 15359,
      "amount": 1,
      "buyer": "Milner",
      "price": 90000,
      "effect": "NOTHING",
      "bonus": 0
    },
    {
      "id": 23020,
      "amount": 6,
      "buyer": "Eco",
      "price": 90000,
      "effect": "NOTHING",
      "bonus": 0
    }
  ]
}