{
  "shop-history": [
    {
      "id": 10946,
      "amount": 5,
      "buyer": "Jroc",
      "price": 45000,
      "effect": "NOTHING",
      "bonus": 0
    },
    {
      "id": 10946,
      "amount": 5,
      "buyer": "Jroc",
      "price": 45000,
      "effect": "NOTHING",
      "bonus": 0
    },
    {
      "id": 10946,
      "amount": 7,
      "buyer": "Entropy",
      "price": 48000,
      "effect": "NOTHING",
      "bonus": 0
    },
    {
      "id": 10946,
      "amount": 10,
      "buyer": "Bookie",
      "price": 48000,
      "effect": "NOTHING",
      "bonus": 0
    },
    {
      "id": 10946,
      "amount": 2,
      "buyer": "Bookie",
      "price": 48000,
      "effect": "NOTHING",
      "bonus": 0
    },
    {
      "id": 23020,
      "amount": 9,
      "buyer": "Onlyfans",
      "price": 40000,
      "effect": "NOTHING",
      "bonus": 0
    },
    {
      "id": 22135,
      "amount": 1,
      "buyer": "Sharp",
      "price": 50000,
      "effect": "RANGE_DAMAGE",
      "bonus": 1
    },
    {
      "id": 14734,
      "amount": 1,
      "buyer": "Sharp",
      "price": 20000,
      "effect": "RANGE_DAMAGE",
      "bonus": 1
    },
    {
      "id": 23020,
      "amount": 5,
      "buyer": "Fishnoob",
      "price": 40000,
      "effect": "NOTHING",
      "bonus": 0
    },
    {
      "id": 19886,
      "amount": 1,
      "buyer": "Jelq",
      "price": 100000,
      "effect": "NOTHING",
      "bonus": 0
    },
    {
      "id": 23057,
      "amount": 1,
      "buyer": "Xtc",
      "price": 590000,
      "effect": "NOTHING",
      "bonus": 0
    },
    {
      "id": 10946,
      "amount": 1,
      "buyer": "Redx12",
      "price": 59000,
      "effect": "NOTHING",
      "bonus": 0
    },
    {
      "id": 23020,
      "amount": 10,
      "buyer": "Vetbrazil",
      "price": 40000,
      "effect": "NOTHING",
      "bonus": 0
    },
    {
      "id": 23020,
      "amount": 2,
      "buyer": "Vetbrazil",
      "price": 40000,
      "effect": "NOTHING",
      "bonus": 0
    },
    {
      "id": 23020,
      "amount": 7,
      "buyer": "Gizeh",
      "price": 10000,
      "effect": "NOTHING",
      "bonus": 0
    },
    {
      "id": 23020,
      "amount": 1,
      "buyer": "Gizeh",
      "price": 10000,
      "effect": "NOTHING",
      "bonus": 0
    },
    {
      "id": 15355,
      "amount": 3,
      "buyer": "Zaryte",
      "price": 250000,
      "effect": "NOTHING",
      "bonus": 0
    },
    {
      "id": 10946,
      "amount": 10,
      "buyer": "Milner",
      "price": 59000,
      "effect": "NOTHING",
      "bonus": 0
    },
    {
      "id": 10946,
      "amount": 5,
      "buyer": "Milner",
      "price": 59000,
      "effect": "NOTHING",
      "bonus": 0
    },
    {
      "id": 10946,
      "amount": 1,
      "buyer": "Milner",
      "price": 59000,
      "effect": "NOTHING",
      "bonus": 0
    },
    {
      "id": 10946,
      "amount": 1,
      "buyer": "Milner",
      "price": 59000,
      "effect": "NOTHING",
      "bonus": 0
    },
    {
      "id": 10946,
      "amount": 58,
      "buyer": "Entropy",
      "price": 59000,
      "effect": "NOTHING",
      "bonus": 0
    },
    {
      "id": 10946,
      "amount": 10,
      "buyer": "Forest",
      "price": 59000,
      "effect": "NOTHING",
      "bonus": 0
    },
    {
      "id": 10946,
      "amount": 10,
      "buyer": "Forest",
      "price": 59000,
      "effect": "NOTHING",
      "bonus": 0
    },
    {
      "id": 10946,
      "amount": 10,
      "buyer": "Forest",
      "price": 59000,
      "effect": "NOTHING",
      "bonus": 0
    },
    {
      "id": 10946,
      "amount": 7,
      "buyer": "Forest",
      "price": 59000,
      "effect": "NOTHING",
      "bonus": 0
    },
    {
      "id": 10946,
      "amount": 1,
      "buyer": "Rayquaza",
      "price": 59000,
      "effect": "NOTHING",
      "bonus": 0
    },
    {
      "id": 10946,
      "amount": 1,
      "buyer": "Rayquaza",
      "price": 59000,
      "effect": "NOTHING",
      "bonus": 0
    },
    {
      "id": 10946,
      "amount": 8,
      "buyer": "Entropy",
      "price": 59000,
      "effect": "NOTHING",
      "bonus": 0
    },
    {
      "id": 10946,
      "amount": 4,
      "buyer": "Bulba",
      "price": 59000,
      "effect": "NOTHING",
      "bonus": 0
    },
    {
      "id": 23071,
      "amount": 1,
      "buyer": "Gor3whor3",
      "price": 25000,
      "effect": "NOTHING",
      "bonus": 0
    },
    {
      "id": 10946,
      "amount": 1,
      "buyer": "Entropy",
      "price": 59000,
      "effect": "NOTHING",
      "bonus": 0
    },
    {
      "id": 23020,
      "amount": 27,
      "buyer": "Netflix",
      "price": 40000,
      "effect": "NOTHING",
      "bonus": 0
    },
    {
      "id": 23020,
      "amount": 5,
      "buyer": "Hc Pvm",
      "price": 40000,
      "effect": "NOTHING",
      "bonus": 0
    },
    {
      "id": 23020,
      "amount": 2,
      "buyer": "Hc Pvm",
      "price": 40000,
      "effect": "NOTHING",
      "bonus": 0
    },
    {
      "id": 23020,
      "amount": 10,
      "buyer": "4bit",
      "price": 40000,
      "effect": "NOTHING",
      "bonus": 0
    },
    {
      "id": 23020,
      "amount": 5,
      "buyer": "Krafty",
      "price": 40000,
      "effect": "NOTHING",
      "bonus": 0
    },
    {
      "id": 23020,
      "amount": 4,
      "buyer": "Rayquaza",
      "price": 40000,
      "effect": "NOTHING",
      "bonus": 0
    },
    {
      "id": 23020,
      "amount": 7,
      "buyer": "3",
      "price": 40000,
      "effect": "NOTHING",
      "bonus": 0
    },
    {
      "id": 23020,
      "amount": 5,
      "buyer": "Krafty",
      "price": 40000,
      "effect": "NOTHING",
      "bonus": 0
    },
    {
      "id": 23020,
      "amount": 10,
      "buyer": "Slayer",
      "price": 40000,
      "effect": "NOTHING",
      "bonus": 0
    },
    {
      "id": 23020,
      "amount": 10,
      "buyer": "Tomzi",
      "price": 40000,
      "effect": "NOTHING",
      "bonus": 0
    },
    {
      "id": 23020,
      "amount": 9,
      "buyer": "Tomzi",
      "price": 40000,
      "effect": "NOTHING",
      "bonus": 0
    },
    {
      "id": 10946,
      "amount": 13,
      "buyer": "Suh",
      "price": 120000,
      "effect": "NOTHING",
      "bonus": 0
    },
    {
      "id": 10946,
      "amount": 9,
      "buyer": "Suh",
      "price": 120000,
      "effect": "NOTHING",
      "bonus": 0
    },
    {
      "id": 23020,
      "amount": 6,
      "buyer": "Netflix",
      "price": 60000,
      "effect": "NOTHING",
      "bonus": 0
    },
    {
      "id": 10946,
      "amount": 10,
      "buyer": "Redx12",
      "price": 90000,
      "effect": "NOTHING",
      "bonus": 0
    },
    {
      "id": 10946,
      "amount": 8,
      "buyer": "Redx12",
      "price": 90000,
      "effect": "NOTHING",
      "bonus": 0
    },
    {
      "id": 23057,
      "amount": 1,
      "buyer": "Redx12",
      "price": 900000,
      "effect": "NOTHING",
      "bonus": 0
    },
    {
      "id": 23020,
      "amount": 10,
      "buyer": "Juust",
      "price": 90000,
      "effect": "NOTHING",
      "bonus": 0
    },
    {
      "id": 23020,
      "amount": 5,
      "buyer": "Juust",
      "price": 90000,
      "effect": "NOTHING",
      "bonus": 0
    },
    {
      "id": 10946,
      "amount": 5,
      "buyer": "Krafty",
      "price": 120000,
      "effect": "NOTHING",
      "bonus": 0
    },
    {
      "id": 10946,
      "amount": 1,
      "buyer": "Krafty",
      "price": 120000,
      "effect": "NOTHING",
      "bonus": 0
    },
    {
      "id": 10946,
      "amount": 10,
      "buyer": "Suh",
      "price": 120000,
      "effect": "NOTHING",
      "bonus": 0
    },
    {
      "id": 10946,
      "amount": 10,
      "buyer": "Suh",
      "price": 120000,
      "effect": "NOTHING",
      "bonus": 0
    },
    {
      "id": 23020,
      "amount": 3,
      "buyer": "Juust",
      "price": 95000,
      "effect": "NOTHING",
      "bonus": 0
    },
    {
      "id": 10946,
      "amount": 45,
      "buyer": "Onlyfans",
      "price": 130000,
      "effect": "NOTHING",
      "bonus": 0
    },
    {
      "id": 10946,
      "amount": 5,
      "buyer": "Princespeach",
      "price": 130000,
      "effect": "NOTHING",
      "bonus": 0
    },
    {
      "id": 10946,
      "amount": 1,
      "buyer": "Princespeach",
      "price": 130000,
      "effect": "NOTHING",
      "bonus": 0
    },
    {
      "id": 10946,
      "amount": 1,
      "buyer": "Princespeach",
      "price": 130000,
      "effect": "NOTHING",
      "bonus": 0
    },
    {
      "id": 10946,
      "amount": 10,
      "buyer": "Jroc",
      "price": 130000,
      "effect": "NOTHING",
      "bonus": 0
    },
    {
      "id": 10946,
      "amount": 9,
      "buyer": "Jroc",
      "price": 130000,
      "effect": "NOTHING",
      "bonus": 0
    },
    {
      "id": 10946,
      "amount": 8,
      "buyer": "Kinda Savage",
      "price": 150000,
      "effect": "NOTHING",
      "bonus": 0
    },
    {
      "id": 10946,
      "amount": 3,
      "buyer": "Kinda Savage",
      "price": 150000,
      "effect": "NOTHING",
      "bonus": 0
    },
    {
      "id": 10946,
      "amount": 8,
      "buyer": "Xtc",
      "price": 150000,
      "effect": "NOTHING",
      "bonus": 0
    },
    {
      "id": 10946,
      "amount": 64,
      "buyer": "Xtc",
      "price": 150000,
      "effect": "NOTHING",
      "bonus": 0
    },
    {
      "id": 10946,
      "amount": 13,
      "buyer": "Xtc",
      "price": 150000,
      "effect": "NOTHING",
      "bonus": 0
    },
    {
      "id": 23057,
      "amount": 1,
      "buyer": "Xtc",
      "price": 1500000,
      "effect": "NOTHING",
      "bonus": 0
    },
    {
      "id": 23057,
      "amount": 3,
      "buyer": "Xtc",
      "price": 1500000,
      "effect": "NOTHING",
      "bonus": 0
    },
    {
      "id": 10946,
      "amount": 21,
      "buyer": "Xtc",
      "price": 150000,
      "effect": "NOTHING",
      "bonus": 0
    },
    {
      "id": 23058,
      "amount": 2,
      "buyer": "Xtc",
      "price": 3750000,
      "effect": "NOTHING",
      "bonus": 0
    },
    {
      "id": 23057,
      "amount": 2,
      "buyer": "Xtc",
      "price": 1500000,
      "effect": "NOTHING",
      "bonus": 0
    },
    {
      "id": 10946,
      "amount": 13,
      "buyer": "Jmaster",
      "price": 160000,
      "effect": "NOTHING",
      "bonus": 0
    },
    {
      "id": 10946,
      "amount": 10,
      "buyer": "Jmaster",
      "price": 160000,
      "effect": "NOTHING",
      "bonus": 0
    },
    {
      "id": 10946,
      "amount": 10,
      "buyer": "Jmaster",
      "price": 160000,
      "effect": "NOTHING",
      "bonus": 0
    },
    {
      "id": 10946,
      "amount": 10,
      "buyer": "Jmaster",
      "price": 160000,
      "effect": "NOTHING",
      "bonus": 0
    },
    {
      "id": 10946,
      "amount": 5,
      "buyer": "Jmaster",
      "price": 160000,
      "effect": "NOTHING",
      "bonus": 0
    },
    {
      "id": 10946,
      "amount": 1,
      "buyer": "Jmaster",
      "price": 160000,
      "effect": "NOTHING",
      "bonus": 0
    },
    {
      "id": 10946,
      "amount": 1,
      "buyer": "Jmaster",
      "price": 160000,
      "effect": "NOTHING",
      "bonus": 0
    },
    {
      "id": 23058,
      "amount": 6,
      "buyer": "Shana",
      "price": 4000000,
      "effect": "NOTHING",
      "bonus": 0
    },
    {
      "id": 23020,
      "amount": 5,
      "buyer": "Tellur",
      "price": 140000,
      "effect": "NOTHING",
      "bonus": 0
    },
    {
      "id": 3086,
      "amount": 1,
      "buyer": "Wbawarrior",
      "price": 3800000,
      "effect": "NOTHING",
      "bonus": 0
    },
    {
      "id": 23020,
      "amount": 1,
      "buyer": "Inherited",
      "price": 140000,
      "effect": "NOTHING",
      "bonus": 0
    },
    {
      "id": 23020,
      "amount": 3,
      "buyer": "Inherited",
      "price": 140000,
      "effect": "NOTHING",
      "bonus": 0
    },
    {
      "id": 19490,
      "amount": 1,
      "buyer": "Domino",
      "price": 200000,
      "effect": "NOTHING",
      "bonus": 0
    },
    {
      "id": 10946,
      "amount": 260,
      "buyer": "Jroc",
      "price": 165000,
      "effect": "NOTHING",
      "bonus": 0
    },
    {
      "id": 23057,
      "amount": 1,
      "buyer": "Jroc",
      "price": 1650000,
      "effect": "NOTHING",
      "bonus": 0
    }
  ]
}